Workbook

Sheet Dashboard
A1: How people use AI at school and at work
A3: Survey of students and professionals across 12 countries | cleaned and analyzed in this workbook | all figures are live formulas
A5: USERS SURVEYED | E5: AI HOURS PER DAY | I5: HOURS SAVED A WEEK | M5: SATISFACTION | Q5: WOULD RECOMMEND | U5: PAY FOR AI
A6: =COUNTA(Clean_Data!$A$2:$A$289) -> 288 | E6: =AVERAGE(Clean_Data!$M$2:$M$289) -> 2.87 | I6: =AVERAGE(Clean_Data!$U$2:$U$289) -> 5.8100719 | M6: =AVERAGE(Clean_Data!$T$2:$T$289) -> 6.1316726 | Q6: =COUNTIFS(Clean_Data!$W$2:$W$289,"Yes")/(COUNTIFS(Clean_Data!$W$2:$W$289,"Yes")+COUNTIFS(Clean_Data!$W$2:$W$289,"Maybe")+COUNTIFS(Clean_Data!$W$2:$W$289,"No")) -> 0.60070671 | U6: =COUNTIFS(Clean_Data!$Q$2:$Q$289,"Paid")/(COUNTIFS(Clean_Data!$Q$2:$Q$289,"Paid")+COUNTIFS(Clean_Data!$Q$2:$Q$289,"Free")) -> 0.4673913
A8: =TEXT(COUNTIFS(Clean_Data!$F$2:$F$289,"Student")/COUNTA(Clean_Data!$A$2:$A$289),"0%")&" students, "&TEXT(COUNTIFS(Clean_Data!$F$2:$F$289,"Professional")/COUNTA(Clean_Data!$A$2:$A$289),"0%")&" professionals" -> 52% students, 48% professionals | E8: average per user | I8: average per user | M8: average score | Q8: answered Yes | U8: on a paid plan
A10: What the data says
A11: ="Tool race: "&INDEX(Analysis!$A$6:$A$13,MATCH(MAX(Analysis!$B$6:$B$13),Analysis!$B$6:$B$13,0))&" is used by "&TEXT(MAX(Analysis!$B$6:$B$13)/SUM(Analysis!$B$6:$B$13),"0%")&" of people. Highest satisfaction among tools with 15+ users: "&INDEX(Analysis!$A$6:$A$13,MATCH(1,INDEX((Analysis!$B$6:$B$13>=15)*(Analysis!$D$6:$D$13=MAX(INDEX((Analysis!$B$6:$B$13>=15)*Analysis!$D$6:$D$13,0))),0),0))&"." -> Tool race: ChatGPT is used by 43% of people. Highest satisfaction among tools with 15+ users: Microsoft Copilot.
A12: ="Students vs professionals: professionals report "&TEXT(Analysis!$C$38,"0.0")&" hrs saved per week, students "&TEXT(Analysis!$B$38,"0.0")&". Average AI use per day: "&TEXT(Analysis!$C$33,"0.0")&" hrs (professionals) vs "&TEXT(Analysis!$B$33,"0.0")&" hrs (students)." -> Students vs professionals: professionals report 5.6 hrs saved per week, students 6.0. Average AI use per day: 2.7 hrs (professionals) vs 3.0 hrs (students).
A13: ="Money: "&TEXT(Analysis!$B$68/(Analysis!$B$68+Analysis!$B$69),"0%")&" of users pay nothing. Paid-plan satisfaction averages "&TEXT(Analysis!$D$69,"0.0")&" vs "&TEXT(Analysis!$D$68,"0.0")&" on free plans." -> Money: 53% of users pay nothing. Paid-plan satisfaction averages 6.0 vs 6.2 on free plans.
A14: ="Time vs payoff: AI hours per day and hours saved per week have a "&LOWER(Analysis!$C$92)&" link (r = "&TEXT(Analysis!$B$92,"0.00")&"). Productivity and satisfaction: "&LOWER(Analysis!$C$94)&" (r = "&TEXT(Analysis!$B$94,"0.00")&")." -> Time vs payoff: AI hours per day and hours saved per week have a strong positive link (r = 0.90). Productivity and satisfaction: strong positive (r = 0.66).
A67: Source: AI_Usage_and_Impact_on_Students_and_Professionals.csv (300 rows, 288 after removing duplicates). Open the Cleaning_Log tab for every change made.

Sheet Analysis
A1: Analysis tables
A2: Every number below is a live formula on the Clean_Data sheet. These tables feed the Dashboard charts. Blank answers are ignored in averages.
A4: 1. AI tools: adoption and results
A5: AI Tool | B5: Users | C5: Share of Tool Answers | D5: Avg Satisfaction (1-10) | E5: Avg Productivity (1-10) | F5: Avg Accuracy (1-5) | G5: % Would Recommend (Yes) | H5: Avg Hrs Saved / Week
A6: ChatGPT | B6: =COUNTIFS(Clean_Data!$K$2:$K$289,$A6) -> 119 | C6: =B6/SUM(B$6:B$13) -> 0.42805755 | D6: =IFERROR(AVERAGEIFS(Clean_Data!$T$2:$T$289,Clean_Data!$K$2:$K$289,$A6),"") -> 6.2608696 | E6: =IFERROR(AVERAGEIFS(Clean_Data!$R$2:$R$289,Clean_Data!$K$2:$K$289,$A6),"") -> 5.2318584 | F6: =IFERROR(AVERAGEIFS(Clean_Data!$S$2:$S$289,Clean_Data!$K$2:$K$289,$A6),"") -> 3.3596491 | G6: =IFERROR(COUNTIFS(Clean_Data!$K$2:$K$289,$A6,Clean_Data!$W$2:$W$289,"Yes")/(COUNTIFS(Clean_Data!$K$2:$K$289,$A6,Clean_Data!$W$2:$W$289,"Yes")+COUNTIFS(Clean_Data!$K$2:$K$289,$A6,Clean_Data!$W$2:$W$289,"Maybe")+COUNTIFS(Clean_Data!$K$2:$K$289,$A6,Clean_Data!$W$2:$W$289,"No")),"") -> 0.58974359 | H6: =IFERROR(AVERAGEIFS(Clean_Data!$U$2:$U$289,Clean_Data!$K$2:$K$289,$A6),"") -> 5.9482759
A7: Google Gemini | B7: =COUNTIFS(Clean_Data!$K$2:$K$289,$A7) -> 39 | C7: =B7/SUM(B$6:B$13) -> 0.14028777 | D7: =IFERROR(AVERAGEIFS(Clean_Data!$T$2:$T$289,Clean_Data!$K$2:$K$289,$A7),"") -> 5.6842105 | E7: =IFERROR(AVERAGEIFS(Clean_Data!$R$2:$R$289,Clean_Data!$K$2:$K$289,$A7),"") -> 5.0605263 | F7: =IFERROR(AVERAGEIFS(Clean_Data!$S$2:$S$289,Clean_Data!$K$2:$K$289,$A7),"") -> 3.3611111 | G7: =IFERROR(COUNTIFS(Clean_Data!$K$2:$K$289,$A7,Clean_Data!$W$2:$W$289,"Yes")/(COUNTIFS(Clean_Data!$K$2:$K$289,$A7,Clean_Data!$W$2:$W$289,"Yes")+COUNTIFS(Clean_Data!$K$2:$K$289,$A7,Clean_Data!$W$2:$W$289,"Maybe")+COUNTIFS(Clean_Data!$K$2:$K$289,$A7,Clean_Data!$W$2:$W$289,"No")),"") -> 0.66666667 | H7: =IFERROR(AVERAGEIFS(Clean_Data!$U$2:$U$289,Clean_Data!$K$2:$K$289,$A7),"") -> 5.3947368
A8: Microsoft Copilot | B8: =COUNTIFS(Clean_Data!$K$2:$K$289,$A8) -> 33 | C8: =B8/SUM(B$6:B$13) -> 0.11870504 | D8: =IFERROR(AVERAGEIFS(Clean_Data!$T$2:$T$289,Clean_Data!$K$2:$K$289,$A8),"") -> 6.3030303 | E8: =IFERROR(AVERAGEIFS(Clean_Data!$R$2:$R$289,Clean_Data!$K$2:$K$289,$A8),"") -> 5.5129032 | F8: =IFERROR(AVERAGEIFS(Clean_Data!$S$2:$S$289,Clean_Data!$K$2:$K$289,$A8),"") -> 3.3939394 | G8: =IFERROR(COUNTIFS(Clean_Data!$K$2:$K$289,$A8,Clean_Data!$W$2:$W$289,"Yes")/(COUNTIFS(Clean_Data!$K$2:$K$289,$A8,Clean_Data!$W$2:$W$289,"Yes")+COUNTIFS(Clean_Data!$K$2:$K$289,$A8,Clean_Data!$W$2:$W$289,"Maybe")+COUNTIFS(Clean_Data!$K$2:$K$289,$A8,Clean_Data!$W$2:$W$289,"No")),"") -> 0.5625 | H8: =IFERROR(AVERAGEIFS(Clean_Data!$U$2:$U$289,Clean_Data!$K$2:$K$289,$A8),"") -> 6.575
A9: Claude | B9: =COUNTIFS(Clean_Data!$K$2:$K$289,$A9) -> 31 | C9: =B9/SUM(B$6:B$13) -> 0.11151079 | D9: =IFERROR(AVERAGEIFS(Clean_Data!$T$2:$T$289,Clean_Data!$K$2:$K$289,$A9),"") -> 6.0967742 | E9: =IFERROR(AVERAGEIFS(Clean_Data!$R$2:$R$289,Clean_Data!$K$2:$K$289,$A9),"") -> 5.2931034 | F9: =IFERROR(AVERAGEIFS(Clean_Data!$S$2:$S$289,Clean_Data!$K$2:$K$289,$A9),"") -> 3.3703704 | G9: =IFERROR(COUNTIFS(Clean_Data!$K$2:$K$289,$A9,Clean_Data!$W$2:$W$289,"Yes")/(COUNTIFS(Clean_Data!$K$2:$K$289,$A9,Clean_Data!$W$2:$W$289,"Yes")+COUNTIFS(Clean_Data!$K$2:$K$289,$A9,Clean_Data!$W$2:$W$289,"Maybe")+COUNTIFS(Clean_Data!$K$2:$K$289,$A9,Clean_Data!$W$2:$W$289,"No")),"") -> 0.61290323 | H9: =IFERROR(AVERAGEIFS(Clean_Data!$U$2:$U$289,Clean_Data!$K$2:$K$289,$A9),"") -> 5.6137931
A10: Perplexity AI | B10: =COUNTIFS(Clean_Data!$K$2:$K$289,$A10) -> 23 | C10: =B10/SUM(B$6:B$13) -> 0.082733813 | D10: =IFERROR(AVERAGEIFS(Clean_Data!$T$2:$T$289,Clean_Data!$K$2:$K$289,$A10),"") -> 5.8181818 | E10: =IFERROR(AVERAGEIFS(Clean_Data!$R$2:$R$289,Clean_Data!$K$2:$K$289,$A10),"") -> 4.64 | F10: =IFERROR(AVERAGEIFS(Clean_Data!$S$2:$S$289,Clean_Data!$K$2:$K$289,$A10),"") -> 3.4090909 | G10: =IFERROR(COUNTIFS(Clean_Data!$K$2:$K$289,$A10,Clean_Data!$W$2:$W$289,"Yes")/(COUNTIFS(Clean_Data!$K$2:$K$289,$A10,Clean_Data!$W$2:$W$289,"Yes")+COUNTIFS(Clean_Data!$K$2:$K$289,$A10,Clean_Data!$W$2:$W$289,"Maybe")+COUNTIFS(Clean_Data!$K$2:$K$289,$A10,Clean_Data!$W$2:$W$289,"No")),"") -> 0.54545455 | H10: =IFERROR(AVERAGEIFS(Clean_Data!$U$2:$U$289,Clean_Data!$K$2:$K$289,$A10),"") -> 5.6363636
A11: Grammarly | B11: =COUNTIFS(Clean_Data!$K$2:$K$289,$A11) -> 14 | C11: =B11/SUM(B$6:B$13) -> 0.050359712 | D11: =IFERROR(AVERAGEIFS(Clean_Data!$T$2:$T$289,Clean_Data!$K$2:$K$289,$A11),"") -> 6.2857143 | E11: =IFERROR(AVERAGEIFS(Clean_Data!$R$2:$R$289,Clean_Data!$K$2:$K$289,$A11),"") -> 5.1142857 | F11: =IFERROR(AVERAGEIFS(Clean_Data!$S$2:$S$289,Clean_Data!$K$2:$K$289,$A11),"") -> 3.8571429 | G11: =IFERROR(COUNTIFS(Clean_Data!$K$2:$K$289,$A11,Clean_Data!$W$2:$W$289,"Yes")/(COUNTIFS(Clean_Data!$K$2:$K$289,$A11,Clean_Data!$W$2:$W$289,"Yes")+COUNTIFS(Clean_Data!$K$2:$K$289,$A11,Clean_Data!$W$2:$W$289,"Maybe")+COUNTIFS(Clean_Data!$K$2:$K$289,$A11,Clean_Data!$W$2:$W$289,"No")),"") -> 0.64285714 | H11: =IFERROR(AVERAGEIFS(Clean_Data!$U$2:$U$289,Clean_Data!$K$2:$K$289,$A11),"") -> 5.4857143
A12: Meta AI | B12: =COUNTIFS(Clean_Data!$K$2:$K$289,$A12) -> 10 | C12: =B12/SUM(B$6:B$13) -> 0.035971223 | D12: =IFERROR(AVERAGEIFS(Clean_Data!$T$2:$T$289,Clean_Data!$K$2:$K$289,$A12),"") -> 6.1 | E12: =IFERROR(AVERAGEIFS(Clean_Data!$R$2:$R$289,Clean_Data!$K$2:$K$289,$A12),"") -> 5.15 | F12: =IFERROR(AVERAGEIFS(Clean_Data!$S$2:$S$289,Clean_Data!$K$2:$K$289,$A12),"") -> 3.5 | G12: =IFERROR(COUNTIFS(Clean_Data!$K$2:$K$289,$A12,Clean_Data!$W$2:$W$289,"Yes")/(COUNTIFS(Clean_Data!$K$2:$K$289,$A12,Clean_Data!$W$2:$W$289,"Yes")+COUNTIFS(Clean_Data!$K$2:$K$289,$A12,Clean_Data!$W$2:$W$289,"Maybe")+COUNTIFS(Clean_Data!$K$2:$K$289,$A12,Clean_Data!$W$2:$W$289,"No")),"") -> 0.4 | H12: =IFERROR(AVERAGEIFS(Clean_Data!$U$2:$U$289,Clean_Data!$K$2:$K$289,$A12),"") -> 4.79
A13: DeepSeek | B13: =COUNTIFS(Clean_Data!$K$2:$K$289,$A13) -> 9 | C13: =B13/SUM(B$6:B$13) -> 0.032374101 | D13: =IFERROR(AVERAGEIFS(Clean_Data!$T$2:$T$289,Clean_Data!$K$2:$K$289,$A13),"") -> 6.125 | E13: =IFERROR(AVERAGEIFS(Clean_Data!$R$2:$R$289,Clean_Data!$K$2:$K$289,$A13),"") -> 5.5333333 | F13: =IFERROR(AVERAGEIFS(Clean_Data!$S$2:$S$289,Clean_Data!$K$2:$K$289,$A13),"") -> 3.75 | G13: =IFERROR(COUNTIFS(Clean_Data!$K$2:$K$289,$A13,Clean_Data!$W$2:$W$289,"Yes")/(COUNTIFS(Clean_Data!$K$2:$K$289,$A13,Clean_Data!$W$2:$W$289,"Yes")+COUNTIFS(Clean_Data!$K$2:$K$289,$A13,Clean_Data!$W$2:$W$289,"Maybe")+COUNTIFS(Clean_Data!$K$2:$K$289,$A13,Clean_Data!$W$2:$W$289,"No")),"") -> 0.625 | H13: =IFERROR(AVERAGEIFS(Clean_Data!$U$2:$U$289,Clean_Data!$K$2:$K$289,$A13),"") -> 6.5571429
A16: 2. What people use AI for
A17: AI Purpose | B17: Users | C17: Students | D17: Professionals | E17: Avg Productivity (1-10) | F17: Avg Hrs Saved / Week
A18: Coding | B18: =COUNTIFS(Clean_Data!$L$2:$L$289,$A18) -> 65 | C18: =COUNTIFS(Clean_Data!$L$2:$L$289,$A18,Clean_Data!$F$2:$F$289,"Student") -> 28 | D18: =COUNTIFS(Clean_Data!$L$2:$L$289,$A18,Clean_Data!$F$2:$F$289,"Professional") -> 37 | E18: =IFERROR(AVERAGEIFS(Clean_Data!$R$2:$R$289,Clean_Data!$L$2:$L$289,$A18),"") -> 4.9444444 | F18: =IFERROR(AVERAGEIFS(Clean_Data!$U$2:$U$289,Clean_Data!$L$2:$L$289,$A18),"") -> 5.625
A19: Writing | B19: =COUNTIFS(Clean_Data!$L$2:$L$289,$A19) -> 49 | C19: =COUNTIFS(Clean_Data!$L$2:$L$289,$A19,Clean_Data!$F$2:$F$289,"Student") -> 29 | D19: =COUNTIFS(Clean_Data!$L$2:$L$289,$A19,Clean_Data!$F$2:$F$289,"Professional") -> 20 | E19: =IFERROR(AVERAGEIFS(Clean_Data!$R$2:$R$289,Clean_Data!$L$2:$L$289,$A19),"") -> 5.5425532 | F19: =IFERROR(AVERAGEIFS(Clean_Data!$U$2:$U$289,Clean_Data!$L$2:$L$289,$A19),"") -> 7.0234043
A20: Studying | B20: =COUNTIFS(Clean_Data!$L$2:$L$289,$A20) -> 39 | C20: =COUNTIFS(Clean_Data!$L$2:$L$289,$A20,Clean_Data!$F$2:$F$289,"Student") -> 39 | D20: =COUNTIFS(Clean_Data!$L$2:$L$289,$A20,Clean_Data!$F$2:$F$289,"Professional") -> 0 | E20: =IFERROR(AVERAGEIFS(Clean_Data!$R$2:$R$289,Clean_Data!$L$2:$L$289,$A20),"") -> 5.0447368 | F20: =IFERROR(AVERAGEIFS(Clean_Data!$U$2:$U$289,Clean_Data!$L$2:$L$289,$A20),"") -> 5.2461538
A21: Research | B21: =COUNTIFS(Clean_Data!$L$2:$L$289,$A21) -> 38 | C21: =COUNTIFS(Clean_Data!$L$2:$L$289,$A21,Clean_Data!$F$2:$F$289,"Student") -> 27 | D21: =COUNTIFS(Clean_Data!$L$2:$L$289,$A21,Clean_Data!$F$2:$F$289,"Professional") -> 11 | E21: =IFERROR(AVERAGEIFS(Clean_Data!$R$2:$R$289,Clean_Data!$L$2:$L$289,$A21),"") -> 5.3514286 | F21: =IFERROR(AVERAGEIFS(Clean_Data!$U$2:$U$289,Clean_Data!$L$2:$L$289,$A21),"") -> 6.2973684
A22: Content Creation | B22: =COUNTIFS(Clean_Data!$L$2:$L$289,$A22) -> 28 | C22: =COUNTIFS(Clean_Data!$L$2:$L$289,$A22,Clean_Data!$F$2:$F$289,"Student") -> 13 | D22: =COUNTIFS(Clean_Data!$L$2:$L$289,$A22,Clean_Data!$F$2:$F$289,"Professional") -> 15 | E22: =IFERROR(AVERAGEIFS(Clean_Data!$R$2:$R$289,Clean_Data!$L$2:$L$289,$A22),"") -> 5.1 | F22: =IFERROR(AVERAGEIFS(Clean_Data!$U$2:$U$289,Clean_Data!$L$2:$L$289,$A22),"") -> 5.4464286
A23: Data Analysis | B23: =COUNTIFS(Clean_Data!$L$2:$L$289,$A23) -> 25 | C23: =COUNTIFS(Clean_Data!$L$2:$L$289,$A23,Clean_Data!$F$2:$F$289,"Student") -> 7 | D23: =COUNTIFS(Clean_Data!$L$2:$L$289,$A23,Clean_Data!$F$2:$F$289,"Professional") -> 18 | E23: =IFERROR(AVERAGEIFS(Clean_Data!$R$2:$R$289,Clean_Data!$L$2:$L$289,$A23),"") -> 5.3954545 | F23: =IFERROR(AVERAGEIFS(Clean_Data!$U$2:$U$289,Clean_Data!$L$2:$L$289,$A23),"") -> 5.1916667
A24: Customer Support | B24: =COUNTIFS(Clean_Data!$L$2:$L$289,$A24) -> 20 | C24: =COUNTIFS(Clean_Data!$L$2:$L$289,$A24,Clean_Data!$F$2:$F$289,"Student") -> 0 | D24: =COUNTIFS(Clean_Data!$L$2:$L$289,$A24,Clean_Data!$F$2:$F$289,"Professional") -> 20 | E24: =IFERROR(AVERAGEIFS(Clean_Data!$R$2:$R$289,Clean_Data!$L$2:$L$289,$A24),"") -> 5.56 | F24: =IFERROR(AVERAGEIFS(Clean_Data!$U$2:$U$289,Clean_Data!$L$2:$L$289,$A24),"") -> 4.8235294
A25: Office Work | B25: =COUNTIFS(Clean_Data!$L$2:$L$289,$A25) -> 11 | C25: =COUNTIFS(Clean_Data!$L$2:$L$289,$A25,Clean_Data!$F$2:$F$289,"Student") -> 0 | D25: =COUNTIFS(Clean_Data!$L$2:$L$289,$A25,Clean_Data!$F$2:$F$289,"Professional") -> 11 | E25: =IFERROR(AVERAGEIFS(Clean_Data!$R$2:$R$289,Clean_Data!$L$2:$L$289,$A25),"") -> 5.9454545 | F25: =IFERROR(AVERAGEIFS(Clean_Data!$U$2:$U$289,Clean_Data!$L$2:$L$289,$A25),"") -> 7.2555556
A28: 3. Students vs professionals
A29: Metric | B29: Student | C29: Professional | D29: All Users
A30: Users | B30: =COUNTIFS(Clean_Data!$F$2:$F$289,"Student") -> 151 | C30: =COUNTIFS(Clean_Data!$F$2:$F$289,"Professional") -> 137 | D30: =COUNTA(Clean_Data!$A$2:$A$289) -> 288
A31: Avg age | B31: =IFERROR(AVERAGEIFS(Clean_Data!$B$2:$B$289,Clean_Data!$F$2:$F$289,"Student"),"") -> 22.191176 | C31: =IFERROR(AVERAGEIFS(Clean_Data!$B$2:$B$289,Clean_Data!$F$2:$F$289,"Professional"),"") -> 37.566929 | D31: =IFERROR(AVERAGE(Clean_Data!$B$2:$B$289),"") -> 29.61597
A32: Avg monthly income | B32: =IFERROR(AVERAGEIFS(Clean_Data!$J$2:$J$289,Clean_Data!$F$2:$F$289,"Student"),"") -> 211.86986 | C32: =IFERROR(AVERAGEIFS(Clean_Data!$J$2:$J$289,Clean_Data!$F$2:$F$289,"Professional"),"") -> 2828.1603 | D32: =IFERROR(AVERAGE(Clean_Data!$J$2:$J$289),"") -> 1449.1769
A33: Avg AI hours / day | B33: =IFERROR(AVERAGEIFS(Clean_Data!$M$2:$M$289,Clean_Data!$F$2:$F$289,"Student"),"") -> 3.0068493 | C33: =IFERROR(AVERAGEIFS(Clean_Data!$M$2:$M$289,Clean_Data!$F$2:$F$289,"Professional"),"") -> 2.7208955 | D33: =IFERROR(AVERAGE(Clean_Data!$M$2:$M$289),"") -> 2.87
A34: Avg work/study hours / day | B34: =IFERROR(AVERAGEIFS(Clean_Data!$N$2:$N$289,Clean_Data!$F$2:$F$289,"Student"),"") -> 6.23125 | C34: =IFERROR(AVERAGEIFS(Clean_Data!$N$2:$N$289,Clean_Data!$F$2:$F$289,"Professional"),"") -> 8.3437037 | D34: =IFERROR(AVERAGE(Clean_Data!$N$2:$N$289),"") -> 7.253405
A35: Avg productivity (1-10) | B35: =IFERROR(AVERAGEIFS(Clean_Data!$R$2:$R$289,Clean_Data!$F$2:$F$289,"Student"),"") -> 5.1923077 | C35: =IFERROR(AVERAGEIFS(Clean_Data!$R$2:$R$289,Clean_Data!$F$2:$F$289,"Professional"),"") -> 5.2816794 | D35: =IFERROR(AVERAGE(Clean_Data!$R$2:$R$289),"") -> 5.2350365
A36: Avg accuracy (1-5) | B36: =IFERROR(AVERAGEIFS(Clean_Data!$S$2:$S$289,Clean_Data!$F$2:$F$289,"Student"),"") -> 3.3661972 | C36: =IFERROR(AVERAGEIFS(Clean_Data!$S$2:$S$289,Clean_Data!$F$2:$F$289,"Professional"),"") -> 3.469697 | D36: =IFERROR(AVERAGE(Clean_Data!$S$2:$S$289),"") -> 3.4160584
A37: Avg satisfaction (1-10) | B37: =IFERROR(AVERAGEIFS(Clean_Data!$T$2:$T$289,Clean_Data!$F$2:$F$289,"Student"),"") -> 6.1866667 | C37: =IFERROR(AVERAGEIFS(Clean_Data!$T$2:$T$289,Clean_Data!$F$2:$F$289,"Professional"),"") -> 6.0687023 | D37: =IFERROR(AVERAGE(Clean_Data!$T$2:$T$289),"") -> 6.1316726
A38: Avg hrs saved / week | B38: =IFERROR(AVERAGEIFS(Clean_Data!$U$2:$U$289,Clean_Data!$F$2:$F$289,"Student"),"") -> 6.0351351 | C38: =IFERROR(AVERAGEIFS(Clean_Data!$U$2:$U$289,Clean_Data!$F$2:$F$289,"Professional"),"") -> 5.5538462 | D38: =IFERROR(AVERAGE(Clean_Data!$U$2:$U$289),"") -> 5.8100719
A39: % on a paid plan | B39: =IFERROR(COUNTIFS(Clean_Data!$Q$2:$Q$289,"Paid",Clean_Data!$F$2:$F$289,"Student")/(COUNTIFS(Clean_Data!$Q$2:$Q$289,"Paid",Clean_Data!$F$2:$F$289,"Student")+COUNTIFS(Clean_Data!$Q$2:$Q$289,"Free",Clean_Data!$F$2:$F$289,"Student")),"") -> 0.47651007 | C39: =IFERROR(COUNTIFS(Clean_Data!$Q$2:$Q$289,"Paid",Clean_Data!$F$2:$F$289,"Professional")/(COUNTIFS(Clean_Data!$Q$2:$Q$289,"Paid",Clean_Data!$F$2:$F$289,"Professional")+COUNTIFS(Clean_Data!$Q$2:$Q$289,"Free",Clean_Data!$F$2:$F$289,"Professional")),"") -> 0.45669291 | D39: =IFERROR(COUNTIFS(Clean_Data!$Q$2:$Q$289,"Paid")/(COUNTIFS(Clean_Data!$Q$2:$Q$289,"Paid")+COUNTIFS(Clean_Data!$Q$2:$Q$289,"Free")),"") -> 0.4673913
A40: % would recommend (Yes) | B40: =IFERROR(COUNTIFS(Clean_Data!$W$2:$W$289,"Yes",Clean_Data!$F$2:$F$289,"Student")/(COUNTIFS(Clean_Data!$W$2:$W$289,"Yes",Clean_Data!$F$2:$F$289,"Student")+COUNTIFS(Clean_Data!$W$2:$W$289,"Maybe",Clean_Data!$F$2:$F$289,"Student")+COUNTIFS(Clean_Data!$W$2:$W$289,"No",Clean_Data!$F$2:$F$289,"Student")),"") -> 0.61073826 | C40: =IFERROR(COUNTIFS(Clean_Data!$W$2:$W$289,"Yes",Clean_Data!$F$2:$F$289,"Professional")/(COUNTIFS(Clean_Data!$W$2:$W$289,"Yes",Clean_Data!$F$2:$F$289,"Professional")+COUNTIFS(Clean_Data!$W$2:$W$289,"Maybe",Clean_Data!$F$2:$F$289,"Professional")+COUNTIFS(Clean_Data!$W$2:$W$289,"No",Clean_Data!$F$2:$F$289,"Professional")),"") -> 0.58955224 | D40: =IFERROR(COUNTIFS(Clean_Data!$W$2:$W$289,"Yes")/(COUNTIFS(Clean_Data!$W$2:$W$289,"Yes")+COUNTIFS(Clean_Data!$W$2:$W$289,"Maybe")+COUNTIFS(Clean_Data!$W$2:$W$289,"No")),"") -> 0.60070671
A43: 4. Top 10 countries by number of users
A44: Country | B44: Users | C44: Avg Satisfaction (1-10) | D44: Avg Hrs Saved / Week
A45: India | B45: =COUNTIFS(Clean_Data!$E$2:$E$289,$A45) -> 43 | C45: =IFERROR(AVERAGEIFS(Clean_Data!$T$2:$T$289,Clean_Data!$E$2:$E$289,$A45),"") -> 6.3571429 | D45: =IFERROR(AVERAGEIFS(Clean_Data!$U$2:$U$289,Clean_Data!$E$2:$E$289,$A45),"") -> 5.2547619
A46: United States | B46: =COUNTIFS(Clean_Data!$E$2:$E$289,$A46) -> 34 | C46: =IFERROR(AVERAGEIFS(Clean_Data!$T$2:$T$289,Clean_Data!$E$2:$E$289,$A46),"") -> 6.0588235 | D46: =IFERROR(AVERAGEIFS(Clean_Data!$U$2:$U$289,Clean_Data!$E$2:$E$289,$A46),"") -> 6.4125
A47: Canada | B47: =COUNTIFS(Clean_Data!$E$2:$E$289,$A47) -> 31 | C47: =IFERROR(AVERAGEIFS(Clean_Data!$T$2:$T$289,Clean_Data!$E$2:$E$289,$A47),"") -> 6.3225806 | D47: =IFERROR(AVERAGEIFS(Clean_Data!$U$2:$U$289,Clean_Data!$E$2:$E$289,$A47),"") -> 6.4933333
A48: Pakistan | B48: =COUNTIFS(Clean_Data!$E$2:$E$289,$A48) -> 28 | C48: =IFERROR(AVERAGEIFS(Clean_Data!$T$2:$T$289,Clean_Data!$E$2:$E$289,$A48),"") -> 5.8214286 | D48: =IFERROR(AVERAGEIFS(Clean_Data!$U$2:$U$289,Clean_Data!$E$2:$E$289,$A48),"") -> 6.48
A49: United Kingdom | B49: =COUNTIFS(Clean_Data!$E$2:$E$289,$A49) -> 26 | C49: =IFERROR(AVERAGEIFS(Clean_Data!$T$2:$T$289,Clean_Data!$E$2:$E$289,$A49),"") -> 6.5384615 | D49: =IFERROR(AVERAGEIFS(Clean_Data!$U$2:$U$289,Clean_Data!$E$2:$E$289,$A49),"") -> 5.7846154
A50: Brazil | B50: =COUNTIFS(Clean_Data!$E$2:$E$289,$A50) -> 26 | C50: =IFERROR(AVERAGEIFS(Clean_Data!$T$2:$T$289,Clean_Data!$E$2:$E$289,$A50),"") -> 6 | D50: =IFERROR(AVERAGEIFS(Clean_Data!$U$2:$U$289,Clean_Data!$E$2:$E$289,$A50),"") -> 4.068
A51: Philippines | B51: =COUNTIFS(Clean_Data!$E$2:$E$289,$A51) -> 24 | C51: =IFERROR(AVERAGEIFS(Clean_Data!$T$2:$T$289,Clean_Data!$E$2:$E$289,$A51),"") -> 6.25 | D51: =IFERROR(AVERAGEIFS(Clean_Data!$U$2:$U$289,Clean_Data!$E$2:$E$289,$A51),"") -> 6.075
A52: Australia | B52: =COUNTIFS(Clean_Data!$E$2:$E$289,$A52) -> 20 | C52: =IFERROR(AVERAGEIFS(Clean_Data!$T$2:$T$289,Clean_Data!$E$2:$E$289,$A52),"") -> 6 | D52: =IFERROR(AVERAGEIFS(Clean_Data!$U$2:$U$289,Clean_Data!$E$2:$E$289,$A52),"") -> 6.445
A53: Nigeria | B53: =COUNTIFS(Clean_Data!$E$2:$E$289,$A53) -> 17 | C53: =IFERROR(AVERAGEIFS(Clean_Data!$T$2:$T$289,Clean_Data!$E$2:$E$289,$A53),"") -> 5.8666667 | D53: =IFERROR(AVERAGEIFS(Clean_Data!$U$2:$U$289,Clean_Data!$E$2:$E$289,$A53),"") -> 5.4375
A54: Germany | B54: =COUNTIFS(Clean_Data!$E$2:$E$289,$A54) -> 13 | C54: =IFERROR(AVERAGEIFS(Clean_Data!$T$2:$T$289,Clean_Data!$E$2:$E$289,$A54),"") -> 5.4166667 | D54: =IFERROR(AVERAGEIFS(Clean_Data!$U$2:$U$289,Clean_Data!$E$2:$E$289,$A54),"") -> 4.5384615
A57: 5. Age groups
A58: Age Group | B58: Users | C58: Avg AI Hours / Day | D58: Avg Hrs Saved / Week | E58: Avg Productivity (1-10)
A59: Under 18 | B59: =COUNTIFS(Clean_Data!$C$2:$C$289,$A59) -> 19 | C59: =IFERROR(AVERAGEIFS(Clean_Data!$M$2:$M$289,Clean_Data!$C$2:$C$289,$A59),"") -> 3.4842105 | D59: =IFERROR(AVERAGEIFS(Clean_Data!$U$2:$U$289,Clean_Data!$C$2:$C$289,$A59),"") -> 6.9526316 | E59: =IFERROR(AVERAGEIFS(Clean_Data!$R$2:$R$289,Clean_Data!$C$2:$C$289,$A59),"") -> 5.6722222
A60: 18-24 | B60: =COUNTIFS(Clean_Data!$C$2:$C$289,$A60) -> 100 | C60: =IFERROR(AVERAGEIFS(Clean_Data!$M$2:$M$289,Clean_Data!$C$2:$C$289,$A60),"") -> 2.98125 | D60: =IFERROR(AVERAGEIFS(Clean_Data!$U$2:$U$289,Clean_Data!$C$2:$C$289,$A60),"") -> 5.9787879 | E60: =IFERROR(AVERAGEIFS(Clean_Data!$R$2:$R$289,Clean_Data!$C$2:$C$289,$A60),"") -> 5.1659794
A61: 25-34 | B61: =COUNTIFS(Clean_Data!$C$2:$C$289,$A61) -> 74 | C61: =IFERROR(AVERAGEIFS(Clean_Data!$M$2:$M$289,Clean_Data!$C$2:$C$289,$A61),"") -> 2.5444444 | D61: =IFERROR(AVERAGEIFS(Clean_Data!$U$2:$U$289,Clean_Data!$C$2:$C$289,$A61),"") -> 5.2273973 | E61: =IFERROR(AVERAGEIFS(Clean_Data!$R$2:$R$289,Clean_Data!$C$2:$C$289,$A61),"") -> 5.173913
A62: 35-44 | B62: =COUNTIFS(Clean_Data!$C$2:$C$289,$A62) -> 42 | C62: =IFERROR(AVERAGEIFS(Clean_Data!$M$2:$M$289,Clean_Data!$C$2:$C$289,$A62),"") -> 2.6390244 | D62: =IFERROR(AVERAGEIFS(Clean_Data!$U$2:$U$289,Clean_Data!$C$2:$C$289,$A62),"") -> 5.3463415 | E62: =IFERROR(AVERAGEIFS(Clean_Data!$R$2:$R$289,Clean_Data!$C$2:$C$289,$A62),"") -> 5.1789474
A63: 45+ | B63: =COUNTIFS(Clean_Data!$C$2:$C$289,$A63) -> 28 | C63: =IFERROR(AVERAGEIFS(Clean_Data!$M$2:$M$289,Clean_Data!$C$2:$C$289,$A63),"") -> 2.5074074 | D63: =IFERROR(AVERAGEIFS(Clean_Data!$U$2:$U$289,Clean_Data!$C$2:$C$289,$A63),"") -> 5.62 | E63: =IFERROR(AVERAGEIFS(Clean_Data!$R$2:$R$289,Clean_Data!$C$2:$C$289,$A63),"") -> 5.1333333
A66: 6. Free vs paid AI plans
A67: Plan | B67: Users | C67: Avg Productivity (1-10) | D67: Avg Satisfaction (1-10) | E67: Avg Hrs Saved / Week | F67: % Would Recommend (Yes)
A68: Free | B68: =COUNTIFS(Clean_Data!$Q$2:$Q$289,$A68) -> 147 | C68: =IFERROR(AVERAGEIFS(Clean_Data!$R$2:$R$289,Clean_Data!$Q$2:$Q$289,$A68),"") -> 5.3985714 | D68: =IFERROR(AVERAGEIFS(Clean_Data!$T$2:$T$289,Clean_Data!$Q$2:$Q$289,$A68),"") -> 6.2394366 | E68: =IFERROR(AVERAGEIFS(Clean_Data!$U$2:$U$289,Clean_Data!$Q$2:$Q$289,$A68),"") -> 5.8381944 | F68: =IFERROR(COUNTIFS(Clean_Data!$Q$2:$Q$289,$A68,Clean_Data!$W$2:$W$289,"Yes")/(COUNTIFS(Clean_Data!$Q$2:$Q$289,$A68,Clean_Data!$W$2:$W$289,"Yes")+COUNTIFS(Clean_Data!$Q$2:$Q$289,$A68,Clean_Data!$W$2:$W$289,"Maybe")+COUNTIFS(Clean_Data!$Q$2:$Q$289,$A68,Clean_Data!$W$2:$W$289,"No")),"") -> 0.66206897
A69: Paid | B69: =COUNTIFS(Clean_Data!$Q$2:$Q$289,$A69) -> 129 | C69: =IFERROR(AVERAGEIFS(Clean_Data!$R$2:$R$289,Clean_Data!$Q$2:$Q$289,$A69),"") -> 5.05 | D69: =IFERROR(AVERAGEIFS(Clean_Data!$T$2:$T$289,Clean_Data!$Q$2:$Q$289,$A69),"") -> 5.976378 | E69: =IFERROR(AVERAGEIFS(Clean_Data!$U$2:$U$289,Clean_Data!$Q$2:$Q$289,$A69),"") -> 5.895082 | F69: =IFERROR(COUNTIFS(Clean_Data!$Q$2:$Q$289,$A69,Clean_Data!$W$2:$W$289,"Yes")/(COUNTIFS(Clean_Data!$Q$2:$Q$289,$A69,Clean_Data!$W$2:$W$289,"Yes")+COUNTIFS(Clean_Data!$Q$2:$Q$289,$A69,Clean_Data!$W$2:$W$289,"Maybe")+COUNTIFS(Clean_Data!$Q$2:$Q$289,$A69,Clean_Data!$W$2:$W$289,"No")),"") -> 0.54761905
A72: 7. Would they recommend it?
A73: Answer | B73: Users | C73: Share
A74: Yes | B74: =COUNTIFS(Clean_Data!$W$2:$W$289,$A74) -> 170 | C74: =B74/SUM(B$74:B$76) -> 0.60070671
A75: Maybe | B75: =COUNTIFS(Clean_Data!$W$2:$W$289,$A75) -> 42 | C75: =B75/SUM(B$74:B$76) -> 0.14840989
A76: No | B76: =COUNTIFS(Clean_Data!$W$2:$W$289,$A76) -> 71 | C76: =B76/SUM(B$74:B$76) -> 0.25088339
A79: 8. Job and field families
A80: Field | B80: Users | C80: Avg AI Hours / Day | D80: Avg Hrs Saved / Week | E80: Avg Productivity (1-10) | F80: Avg Satisfaction (1-10)
A81: Content, Media & Writing | B81: =COUNTIFS(Clean_Data!$I$2:$I$289,$A81) -> 77 | C81: =IFERROR(AVERAGEIFS(Clean_Data!$M$2:$M$289,Clean_Data!$I$2:$I$289,$A81),"") -> 3.1616438 | D81: =IFERROR(AVERAGEIFS(Clean_Data!$U$2:$U$289,Clean_Data!$I$2:$I$289,$A81),"") -> 6.4106667 | E81: =IFERROR(AVERAGEIFS(Clean_Data!$R$2:$R$289,Clean_Data!$I$2:$I$289,$A81),"") -> 5.3666667 | F81: =IFERROR(AVERAGEIFS(Clean_Data!$T$2:$T$289,Clean_Data!$I$2:$I$289,$A81),"") -> 6.2638889
A82: Software & IT | B82: =COUNTIFS(Clean_Data!$I$2:$I$289,$A82) -> 74 | C82: =IFERROR(AVERAGEIFS(Clean_Data!$M$2:$M$289,Clean_Data!$I$2:$I$289,$A82),"") -> 2.5597222 | D82: =IFERROR(AVERAGEIFS(Clean_Data!$U$2:$U$289,Clean_Data!$I$2:$I$289,$A82),"") -> 5.4616438 | E82: =IFERROR(AVERAGEIFS(Clean_Data!$R$2:$R$289,Clean_Data!$I$2:$I$289,$A82),"") -> 4.9887324 | F82: =IFERROR(AVERAGEIFS(Clean_Data!$T$2:$T$289,Clean_Data!$I$2:$I$289,$A82),"") -> 5.8378378
A83: Data & Analytics | B83: =COUNTIFS(Clean_Data!$I$2:$I$289,$A83) -> 38 | C83: =IFERROR(AVERAGEIFS(Clean_Data!$M$2:$M$289,Clean_Data!$I$2:$I$289,$A83),"") -> 2.5289474 | D83: =IFERROR(AVERAGEIFS(Clean_Data!$U$2:$U$289,Clean_Data!$I$2:$I$289,$A83),"") -> 5.0171429 | E83: =IFERROR(AVERAGEIFS(Clean_Data!$R$2:$R$289,Clean_Data!$I$2:$I$289,$A83),"") -> 5.2625 | F83: =IFERROR(AVERAGEIFS(Clean_Data!$T$2:$T$289,Clean_Data!$I$2:$I$289,$A83),"") -> 6
A84: Science & Research | B84: =COUNTIFS(Clean_Data!$I$2:$I$289,$A84) -> 38 | C84: =IFERROR(AVERAGEIFS(Clean_Data!$M$2:$M$289,Clean_Data!$I$2:$I$289,$A84),"") -> 2.9111111 | D84: =IFERROR(AVERAGEIFS(Clean_Data!$U$2:$U$289,Clean_Data!$I$2:$I$289,$A84),"") -> 5.8026316 | E84: =IFERROR(AVERAGEIFS(Clean_Data!$R$2:$R$289,Clean_Data!$I$2:$I$289,$A84),"") -> 5.1657895 | F84: =IFERROR(AVERAGEIFS(Clean_Data!$T$2:$T$289,Clean_Data!$I$2:$I$289,$A84),"") -> 6.7297297
A85: Customer Support | B85: =COUNTIFS(Clean_Data!$I$2:$I$289,$A85) -> 21 | C85: =IFERROR(AVERAGEIFS(Clean_Data!$M$2:$M$289,Clean_Data!$I$2:$I$289,$A85),"") -> 2.8380952 | D85: =IFERROR(AVERAGEIFS(Clean_Data!$U$2:$U$289,Clean_Data!$I$2:$I$289,$A85),"") -> 4.9055556 | E85: =IFERROR(AVERAGEIFS(Clean_Data!$R$2:$R$289,Clean_Data!$I$2:$I$289,$A85),"") -> 5.5380952 | F85: =IFERROR(AVERAGEIFS(Clean_Data!$T$2:$T$289,Clean_Data!$I$2:$I$289,$A85),"") -> 6.1
A86: Engineering | B86: =COUNTIFS(Clean_Data!$I$2:$I$289,$A86) -> 13 | C86: =IFERROR(AVERAGEIFS(Clean_Data!$M$2:$M$289,Clean_Data!$I$2:$I$289,$A86),"") -> 2.9 | D86: =IFERROR(AVERAGEIFS(Clean_Data!$U$2:$U$289,Clean_Data!$I$2:$I$289,$A86),"") -> 5.4846154 | E86: =IFERROR(AVERAGEIFS(Clean_Data!$R$2:$R$289,Clean_Data!$I$2:$I$289,$A86),"") -> 4.975 | F86: =IFERROR(AVERAGEIFS(Clean_Data!$T$2:$T$289,Clean_Data!$I$2:$I$289,$A86),"") -> 5.6923077
A87: Business & Admin | B87: =COUNTIFS(Clean_Data!$I$2:$I$289,$A87) -> 13 | C87: =IFERROR(AVERAGEIFS(Clean_Data!$M$2:$M$289,Clean_Data!$I$2:$I$289,$A87),"") -> 3.9 | D87: =IFERROR(AVERAGEIFS(Clean_Data!$U$2:$U$289,Clean_Data!$I$2:$I$289,$A87),"") -> 7.6076923 | E87: =IFERROR(AVERAGEIFS(Clean_Data!$R$2:$R$289,Clean_Data!$I$2:$I$289,$A87),"") -> 6.0076923 | F87: =IFERROR(AVERAGEIFS(Clean_Data!$T$2:$T$289,Clean_Data!$I$2:$I$289,$A87),"") -> 6.3846154
A90: 9. What moves together? (correlations) | E90: r near +1 or -1 = strong link. Correlation is not cause.
A91: Pair | B91: r | C91: Reading
A92: AI hours per day vs hours saved per week | B92: =IFERROR(CORREL(Clean_Data!$M$2:$M$289,Clean_Data!$U$2:$U$289),"") -> 0.89790323 | C92: =IF(B92="","",IF(ABS(B92)>=0.5,"Strong",IF(ABS(B92)>=0.3,"Moderate",IF(ABS(B92)>=0.1,"Weak","Negligible")))&IF(B92>=0," positive"," negative")) -> Strong positive
A93: AI hours per day vs productivity | B93: =IFERROR(CORREL(Clean_Data!$M$2:$M$289,Clean_Data!$R$2:$R$289),"") -> 0.78054402 | C93: =IF(B93="","",IF(ABS(B93)>=0.5,"Strong",IF(ABS(B93)>=0.3,"Moderate",IF(ABS(B93)>=0.1,"Weak","Negligible")))&IF(B93>=0," positive"," negative")) -> Strong positive
A94: Productivity vs satisfaction | B94: =IFERROR(CORREL(Clean_Data!$R$2:$R$289,Clean_Data!$T$2:$T$289),"") -> 0.65635201 | C94: =IF(B94="","",IF(ABS(B94)>=0.5,"Strong",IF(ABS(B94)>=0.3,"Moderate",IF(ABS(B94)>=0.1,"Weak","Negligible")))&IF(B94>=0," positive"," negative")) -> Strong positive
A95: Accuracy rating vs satisfaction | B95: =IFERROR(CORREL(Clean_Data!$S$2:$S$289,Clean_Data!$T$2:$T$289),"") -> 0.52193448 | C95: =IF(B95="","",IF(ABS(B95)>=0.5,"Strong",IF(ABS(B95)>=0.3,"Moderate",IF(ABS(B95)>=0.1,"Weak","Negligible")))&IF(B95>=0," positive"," negative")) -> Strong positive
A96: Monthly AI cost vs satisfaction | B96: =IFERROR(CORREL(Clean_Data!$P$2:$P$289,Clean_Data!$T$2:$T$289),"") -> 0.022945909 | C96: =IF(B96="","",IF(ABS(B96)>=0.5,"Strong",IF(ABS(B96)>=0.3,"Moderate",IF(ABS(B96)>=0.1,"Weak","Negligible")))&IF(B96>=0," positive"," negative")) -> Negligible positive
A97: Age vs AI hours per day | B97: =IFERROR(CORREL(Clean_Data!$B$2:$B$289,Clean_Data!$M$2:$M$289),"") -> -0.097281705 | C97: =IF(B97="","",IF(ABS(B97)>=0.5,"Strong",IF(ABS(B97)>=0.3,"Moderate",IF(ABS(B97)>=0.1,"Weak","Negligible")))&IF(B97>=0," positive"," negative")) -> Negligible negative

Sheet Clean_Data
A1: User_ID | B1: Age | C1: Age_Group | D1: Gender | E1: Country | F1: User_Type | G1: Education_Level | H1: Profession | I1: Profession_Group | J1: Monthly_Income | K1: AI_Tool | L1: AI_Purpose | M1: AI_Hours_Per_Day | N1: Work_Study_Hours_Per_Day | O1: AI_Share_of_Day | P1: Monthly_AI_Cost | Q1: Plan_Type | R1: Productivity_Score | S1: Accuracy_Rating | T1: Satisfaction_Score | U1: Time_Saved_Hours_Per_Week | V1: Hours_Saved_per_AI_Hour | W1: Would_Recommend | X1: Data_Flags | Y1: Tasks_Performed
A2: U0269 | B2: 30 | C2: =IF(B2="","",IF(B2<18,"Under 18",IF(B2<25,"18-24",IF(B2<35,"25-34",IF(B2<45,"35-44","45+"))))) -> 25-34 | D2: Male | E2: United Kingdom | F2: Professional | G2: Master's | H2: Business Analyst | I2: Data & Analytics | J2: 5421 | K2: ChatGPT | L2: Office Work | M2: 2 | N2: 7.3 | O2: =IF(OR(M2="",N2=""),"",M2/N2) -> 0.2739726 | Q2: =IF(P2="","",IF(P2=0,"Free","Paid")) | R2: 5.3 | S2: 4 | T2: 7 | U2: 3.9 | V2: =IF(OR(U2="",M2="",M2=0),"",U2/(M2*7)) -> 0.27857143 | W2: Yes | Y2: Data analysis using AI-powered analytics tools, automated report generation, process optimization modelling, AI-assisted business intelligence reporting
A3: U0217 | B3: 30 | C3: =IF(B3="","",IF(B3<18,"Under 18",IF(B3<25,"18-24",IF(B3<35,"25-34",IF(B3<45,"35-44","45+"))))) -> 25-34 | D3: Male | E3: United States | F3: Professional | G3: Bachelor's | H3: Customer Support Specialist | I3: Customer Support | J3: 8903 | K3: ChatGPT | L3: Customer Support | M3: 5.7 | N3: 8.4 | O3: =IF(OR(M3="",N3=""),"",M3/N3) -> 0.67857143 | P3: 0 | Q3: =IF(P3="","",IF(P3=0,"Free","Paid")) -> Free | R3: 9.9 | S3: 3 | T3: 9 | U3: 11.4 | V3: =IF(OR(U3="",M3="",M3=0),"",U3/(M3*7)) -> 0.28571429 | W3: Yes | Y3: Resolving customer inquiries using AI chatbot platforms, drafting personalized email responses with AI writing assistants, analyzing customer sentiment with AI tools, managing support tickets with AI-powered ticketing systems
A4: U0152 | B4: 17 | C4: =IF(B4="","",IF(B4<18,"Under 18",IF(B4<25,"18-24",IF(B4<35,"25-34",IF(B4<45,"35-44","45+"))))) -> Under 18 | D4: Male | E4: Canada | F4: Student | H4: Computer Science Student | I4: Software & IT | J4: 402 | K4: ChatGPT | L4: Coding | M4: 1 | N4: 6.7 | O4: =IF(OR(M4="",N4=""),"",M4/N4) -> 0.14925373 | P4: 20 | Q4: =IF(P4="","",IF(P4=0,"Free","Paid")) -> Paid | R4: 3.2 | S4: 2 | T4: 4 | U4: 5.2 | V4: =IF(OR(U4="",M4="",M4=0),"",U4/(M4*7)) -> 0.74285714 | W4: No
A5: U0264 | B5: 35 | C5: =IF(B5="","",IF(B5<18,"Under 18",IF(B5<25,"18-24",IF(B5<35,"25-34",IF(B5<45,"35-44","45+"))))) -> 35-44 | D5: Female | E5: Brazil | F5: Professional | G5: Bachelor's | H5: Desenvolvedora de Software / Software Developer | I5: Software & IT | J5: 1367 | K5: Meta AI | L5: Coding | M5: 1.7 | N5: 9.6 | O5: =IF(OR(M5="",N5=""),"",M5/N5) -> 0.17708333 | P5: 20 | Q5: =IF(P5="","",IF(P5=0,"Free","Paid")) -> Paid | R5: 5.6 | S5: 4 | T5: 5 | U5: 6.4 | V5: =IF(OR(U5="",M5="",M5=0),"",U5/(M5*7)) -> 0.53781513 | W5: Maybe | Y5: Usar GitHub Copilot para autocompletar código, debugar aplicações com assistência de IA, otimizar algoritmos com sugestões de IA, revisar e refatorar código existente
A6: U0263 | B6: 19 | C6: =IF(B6="","",IF(B6<18,"Under 18",IF(B6<25,"18-24",IF(B6<35,"25-34",IF(B6<45,"35-44","45+"))))) -> 18-24 | D6: Female | E6: Canada | F6: Student | G6: Undergraduate | H6: Biology Student | I6: Science & Research | J6: 438 | K6: Perplexity AI | M6: 4.1 | N6: 6.2 | O6: =IF(OR(M6="",N6=""),"",M6/N6) -> 0.66129032 | P6: 0 | Q6: =IF(P6="","",IF(P6=0,"Free","Paid")) -> Free | R6: 4.7 | S6: 4 | T6: 7 | U6: 9.2 | V6: =IF(OR(U6="",M6="",M6=0),"",U6/(M6*7)) -> 0.32055749 | W6: Yes | Y6: Using AI to generate study summaries for exam preparation, getting help with practice problem solutions, organizing research paper notes
A7: U0225 | B7: 19 | C7: =IF(B7="","",IF(B7<18,"Under 18",IF(B7<25,"18-24",IF(B7<35,"25-34",IF(B7<45,"35-44","45+"))))) -> 18-24 | E7: United States | F7: Student | G7: Undergraduate | H7: Business Analytics Student | I7: Data & Analytics | J7: 774 | K7: Meta AI | L7: Data Analysis | M7: 1.5 | N7: 7.4 | O7: =IF(OR(M7="",N7=""),"",M7/N7) -> 0.2027027 | P7: 0 | Q7: =IF(P7="","",IF(P7=0,"Free","Paid")) -> Free | R7: 5 | S7: 3 | T7: 6 | U7: 2.9 | V7: =IF(OR(U7="",M7="",M7=0),"",U7/(M7*7)) -> 0.27619048 | W7: No | Y7: Statistical analysis on datasets, data visualization with Python libraries, predictive modeling for coursework, business intelligence report generation
A8: U0246 | B8: 32 | C8: =IF(B8="","",IF(B8<18,"Under 18",IF(B8<25,"18-24",IF(B8<35,"25-34",IF(B8<45,"35-44","45+"))))) -> 25-34 | D8: Male | E8: France | F8: Professional | G8: Bachelor's | H8: Développeur Full Stack | I8: Software & IT | J8: 4466 | K8: ChatGPT | L8: Coding | M8: 1.2 | N8: 6.4 | O8: =IF(OR(M8="",N8=""),"",M8/N8) -> 0.1875 | P8: 20 | Q8: =IF(P8="","",IF(P8=0,"Free","Paid")) -> Paid | R8: 3 | S8: 2 | T8: 5 | U8: 6.6 | V8: =IF(OR(U8="",M8="",M8=0),"",U8/(M8*7)) -> 0.78571429 | W8: Yes | Y8: Automated code review with AI-powered linters, Generated boilerplate code and API endpoints using GitHub Copilot, Debugged complex algorithms with AI assistance, Optimized database queries using AI suggestions
A9: U0177 | B9: 32 | C9: =IF(B9="","",IF(B9<18,"Under 18",IF(B9<25,"18-24",IF(B9<35,"25-34",IF(B9<45,"35-44","45+"))))) -> 25-34 | D9: Male | E9: Philippines | F9: Professional | G9: High School | H9: Social Media Content Creator | I9: Content, Media & Writing | J9: 486 | K9: ChatGPT | L9: Content Creation | M9: 2 | N9: 6.4 | O9: =IF(OR(M9="",N9=""),"",M9/N9) -> 0.3125 | P9: 0 | Q9: =IF(P9="","",IF(P9=0,"Free","Paid")) -> Free | R9: 6.5 | S9: 2 | T9: 5 | U9: 3.2 | V9: =IF(OR(U9="",M9="",M9=0),"",U9/(M9*7)) -> 0.22857143 | W9: Yes | Y9: Creating Instagram/TikTok captions with AI writing tools, Generating YouTube thumbnails and video descriptions using AI design assistants, Editing photos and videos with AI-powered software
A10: U0207 | B10: 16 | C10: =IF(B10="","",IF(B10<18,"Under 18",IF(B10<25,"18-24",IF(B10<35,"25-34",IF(B10<45,"35-44","45+"))))) -> Under 18 | D10: Male | E10: Philippines | F10: Student | G10: Undergraduate | H10: Digital Media Production Student | I10: Content, Media & Writing | J10: 132 | K10: Claude | L10: Content Creation | M10: 1.6 | N10: 3.8 | O10: =IF(OR(M10="",N10=""),"",M10/N10) -> 0.42105263 | P10: 30 | Q10: =IF(P10="","",IF(P10=0,"Free","Paid")) -> Paid | R10: 4.7 | S10: 4 | T10: 6 | U10: 3.8 | V10: =IF(OR(U10="",M10="",M10=0),"",U10/(M10*7)) -> 0.33928571 | W10: Yes | Y10: Creating YouTube video scripts, Designing social media graphics with AI image generators, Writing blog content for tech topics
A11: U0167 | B11: 40 | C11: =IF(B11="","",IF(B11<18,"Under 18",IF(B11<25,"18-24",IF(B11<35,"25-34",IF(B11<45,"35-44","45+"))))) -> 35-44 | D11: Male | E11: India | F11: Professional | G11: High School | J11: 1595 | K11: ChatGPT | L11: Writing | M11: 1.7 | N11: 9.4 | O11: =IF(OR(M11="",N11=""),"",M11/N11) -> 0.18085106 | P11: 10 | Q11: =IF(P11="","",IF(P11=0,"Free","Paid")) -> Paid | S11: 2 | T11: 5 | U11: 7.5 | V11: =IF(OR(U11="",M11="",M11=0),"",U11/(M11*7)) -> 0.6302521 | W11: Maybe | Y11: Email copywriting, Social media post creation, Blog article drafting, Product description writing
A12: U0135 | B12: 36 | C12: =IF(B12="","",IF(B12<18,"Under 18",IF(B12<25,"18-24",IF(B12<35,"25-34",IF(B12<45,"35-44","45+"))))) -> 35-44 | D12: Female | E12: Pakistan | F12: Professional | G12: Master's | H12: Research Analyst | I12: Data & Analytics | J12: 856 | K12: ChatGPT | L12: Research | M12: 2.7 | N12: 8.7 | O12: =IF(OR(M12="",N12=""),"",M12/N12) -> 0.31034483 | P12: 0 | Q12: =IF(P12="","",IF(P12=0,"Free","Paid")) -> Free | S12: 4 | T12: 6 | U12: 5.7 | V12: =IF(OR(U12="",M12="",M12=0),"",U12/(M12*7)) -> 0.3015873 | W12: Yes | Y12: Literature review and synthesis using AI-powered databases, Data analysis and pattern recognition, Research paper writing and academic content generation
A13: U0211 | B13: 22 | C13: =IF(B13="","",IF(B13<18,"Under 18",IF(B13<25,"18-24",IF(B13<35,"25-34",IF(B13<45,"35-44","45+"))))) -> 18-24 | D13: Male | E13: Canada | F13: Student | G13: Undergraduate | H13: Mechanical Engineering Student | I13: Engineering | J13: 547 | K13: Claude | L13: Research | M13: 5 | N13: 5.6 | O13: =IF(OR(M13="",N13=""),"",M13/N13) -> 0.89285714 | P13: 0 | Q13: =IF(P13="","",IF(P13=0,"Free","Paid")) -> Free | R13: 6.6 | S13: 3 | T13: 6 | U13: 9.8 | V13: =IF(OR(U13="",M13="",M13=0),"",U13/(M13*7)) -> 0.28 | W13: No | Y13: Literature review and paper summarization, Data analysis for lab experiments, Generating research hypotheses, Technical documentation and report writing
A14: U0114 | B14: 30 | C14: =IF(B14="","",IF(B14<18,"Under 18",IF(B14<25,"18-24",IF(B14<35,"25-34",IF(B14<45,"35-44","45+"))))) -> 25-34 | D14: Female | E14: Australia | F14: Professional | G14: Bachelor's | H14: Software Developer | I14: Software & IT | J14: 3307 | K14: ChatGPT | L14: Coding | M14: 0.8 | N14: 8 | O14: =IF(OR(M14="",N14=""),"",M14/N14) -> 0.1 | P14: 10 | Q14: =IF(P14="","",IF(P14=0,"Free","Paid")) -> Paid | R14: 2.3 | S14: 4 | T14: 4 | U14: 0.5 | V14: =IF(OR(U14="",M14="",M14=0),"",U14/(M14*7)) -> 0.089285714 | W14: No | Y14: Using AI code completion tools for writing Python functions, debugging code with AI-assisted analysis, generating unit test cases with AI tools
A15: U0191 | B15: 21 | C15: =IF(B15="","",IF(B15<18,"Under 18",IF(B15<25,"18-24",IF(B15<35,"25-34",IF(B15<45,"35-44","45+"))))) -> 18-24 | D15: Female | E15: Canada | F15: Student | G15: Undergraduate | H15: Software Engineering Student | I15: Software & IT | J15: 387 | K15: ChatGPT | L15: Coding | M15: 5.8 | N15: 4.8 | O15: =IF(OR(M15="",N15=""),"",M15/N15) -> 1.2083333 | P15: 30 | Q15: =IF(P15="","",IF(P15=0,"Free","Paid")) -> Paid | R15: 6.9 | S15: 4 | T15: 8 | U15: 10.2 | V15: =IF(OR(U15="",M15="",M15=0),"",U15/(M15*7)) -> 0.25123153 | W15: Yes | X15: AI hrs exceed work/study hrs (kept) | Y15: Debugging code with AI assistance, generating code snippets for assignments, learning programming concepts through AI explanations
A16: U0035 | B16: 28 | C16: =IF(B16="","",IF(B16<18,"Under 18",IF(B16<25,"18-24",IF(B16<35,"25-34",IF(B16<45,"35-44","45+"))))) -> 25-34 | D16: Male | E16: United Kingdom | F16: Professional | G16: Bachelor's | H16: Data Analyst | I16: Data & Analytics | J16: 3117 | K16: Claude | L16: Data Analysis | M16: 3.9 | N16: 7.6 | O16: =IF(OR(M16="",N16=""),"",M16/N16) -> 0.51315789 | P16: 10 | Q16: =IF(P16="","",IF(P16=0,"Free","Paid")) -> Paid | R16: 8.6 | S16: 3 | T16: 8 | U16: 11.8 | V16: =IF(OR(U16="",M16="",M16=0),"",U16/(M16*7)) -> 0.43223443 | W16: Yes | Y16: Automated data cleaning and processing with Python scripts, building predictive models using machine learning algorithms, generating interactive dashboards and visualizations in Power BI
A17: U0138 | B17: 16 | C17: =IF(B17="","",IF(B17<18,"Under 18",IF(B17<25,"18-24",IF(B17<35,"25-34",IF(B17<45,"35-44","45+"))))) -> Under 18 | D17: Female | E17: Canada | F17: Student | G17: Master's | J17: 324 | K17: Microsoft Copilot | L17: Coding | M17: 7.1 | N17: 3 | O17: =IF(OR(M17="",N17=""),"",M17/N17) -> 2.3666667 | P17: 20 | Q17: =IF(P17="","",IF(P17=0,"Free","Paid")) -> Paid | S17: 2 | T17: 5 | U17: 11.6 | V17: =IF(OR(U17="",M17="",M17=0),"",U17/(M17*7)) -> 0.2334004 | W17: No | X17: AI hrs exceed work/study hrs (kept)
A18: U0059 | B18: 22 | C18: =IF(B18="","",IF(B18<18,"Under 18",IF(B18<25,"18-24",IF(B18<35,"25-34",IF(B18<45,"35-44","45+"))))) -> 18-24 | D18: Male | E18: Canada | F18: Professional | G18: High School | H18: Customer Service Representative | I18: Customer Support | J18: 3546 | K18: Perplexity AI | L18: Customer Support | M18: 1.7 | N18: 6.7 | O18: =IF(OR(M18="",N18=""),"",M18/N18) -> 0.25373134 | P18: 0 | Q18: =IF(P18="","",IF(P18=0,"Free","Paid")) -> Free | R18: 7 | S18: 4 | T18: 7 | U18: 3.4 | V18: =IF(OR(U18="",M18="",M18=0),"",U18/(M18*7)) -> 0.28571429 | W18: Yes | Y18: Responding to customer inquiries via AI chatbots, drafting personalized support emails using AI writing assistants, resolving common technical issues with AI-guided troubleshooting scripts
A19: U0215 | B19: 23 | C19: =IF(B19="","",IF(B19<18,"Under 18",IF(B19<25,"18-24",IF(B19<35,"25-34",IF(B19<45,"35-44","45+"))))) -> 18-24 | D19: Male | E19: India | F19: Student | G19: Master's | H19: English Literature Student | I19: Content, Media & Writing | J19: 109 | K19: Google Gemini | L19: Writing | M19: 1.5 | N19: 3.9 | O19: =IF(OR(M19="",N19=""),"",M19/N19) -> 0.38461538 | P19: 20 | Q19: =IF(P19="","",IF(P19=0,"Free","Paid")) -> Paid | R19: 3.9 | S19: 3 | T19: 6 | U19: 3.7 | V19: =IF(OR(U19="",M19="",M19=0),"",U19/(M19*7)) -> 0.35238095 | W19: Yes | Y19: Drafting research papers on literary analysis, brainstorming essay outlines, proofreading and refining academic writing, generating content summaries for thesis work
A20: U0228 | B20: 22 | C20: =IF(B20="","",IF(B20<18,"Under 18",IF(B20<25,"18-24",IF(B20<35,"25-34",IF(B20<45,"35-44","45+"))))) -> 18-24 | D20: Male | E20: Kenya | F20: Student | G20: High School | H20: Biology Student | I20: Science & Research | J20: 109 | K20: ChatGPT | L20: Research | M20: 9.6 | N20: 5.2 | O20: =IF(OR(M20="",N20=""),"",M20/N20) -> 1.8461538 | P20: 20 | Q20: =IF(P20="","",IF(P20=0,"Free","Paid")) -> Paid | R20: 7.3 | S20: 4 | T20: 9 | U20: 19.4 | V20: =IF(OR(U20="",M20="",M20=0),"",U20/(M20*7)) -> 0.28869048 | W20: Yes | X20: AI hrs exceed work/study hrs (kept) | Y20: Literature review for lab reports, summarizing research papers on molecular genetics, generating study notes from scientific articles
A21: U0046 | B21: 61 | C21: =IF(B21="","",IF(B21<18,"Under 18",IF(B21<25,"18-24",IF(B21<35,"25-34",IF(B21<45,"35-44","45+"))))) -> 45+ | D21: Female | E21: Nigeria | F21: Professional | G21: Diploma | H21: Research Technician | I21: Science & Research | J21: 585 | K21: Google Gemini | L21: Research | N21: 9.5 | O21: =IF(OR(M21="",N21=""),"",M21/N21) | P21: 10 | Q21: =IF(P21="","",IF(P21=0,"Free","Paid")) -> Paid | R21: 4.1 | S21: 3 | T21: 4 | U21: 5.4 | V21: =IF(OR(U21="",M21="",M21=0),"",U21/(M21*7)) | W21: No | X21: AI hrs/day over 16, blanked | Y21: Literature review synthesis using AI search tools, Data analysis and statistical reporting with AI-assisted tools, Survey data organization and preliminary findings documentation
A22: U0176 | B22: 24 | C22: =IF(B22="","",IF(B22<18,"Under 18",IF(B22<25,"18-24",IF(B22<35,"25-34",IF(B22<45,"35-44","45+"))))) -> 18-24 | D22: Male | E22: India | F22: Professional | G22: Diploma | H22: AI-Powered Customer Support Executive | I22: Customer Support | J22: 1977 | K22: ChatGPT | L22: Customer Support | M22: 0.9 | N22: 7.3 | O22: =IF(OR(M22="",N22=""),"",M22/N22) -> 0.12328767 | P22: 10 | Q22: =IF(P22="","",IF(P22=0,"Free","Paid")) -> Paid | R22: 4.1 | S22: 3 | T22: 6 | U22: 0 | V22: =IF(OR(U22="",M22="",M22=0),"",U22/(M22*7)) -> 0 | W22: Maybe | Y22: AI chatbot management and customer query routing, multilingual customer response handling using AI tools, customer complaint analysis and resolution tracking
A23: U0227 | B23: 23 | C23: =IF(B23="","",IF(B23<18,"Under 18",IF(B23<25,"18-24",IF(B23<35,"25-34",IF(B23<45,"35-44","45+"))))) -> 18-24 | D23: Male | E23: Pakistan | F23: Student | G23: Master's | H23: English Literature Student | I23: Content, Media & Writing | J23: 0 | K23: ChatGPT | L23: Writing | M23: 1.7 | N23: 5.4 | O23: =IF(OR(M23="",N23=""),"",M23/N23) -> 0.31481481 | P23: 20 | Q23: =IF(P23="","",IF(P23=0,"Free","Paid")) -> Paid | R23: 2.8 | S23: 2 | T23: 3 | U23: 2.7 | V23: =IF(OR(U23="",M23="",M23=0),"",U23/(M23*7)) -> 0.22689076 | W23: No | Y23: Essay structuring and outline generation, thesis statement refinement, academic paper proofreading and grammar checking, creative writing brainstorming
A24: U0198 | B24: 29 | C24: =IF(B24="","",IF(B24<18,"Under 18",IF(B24<25,"18-24",IF(B24<35,"25-34",IF(B24<45,"35-44","45+"))))) -> 25-34 | D24: Female | E24: Germany | F24: Professional | G24: Bachelor's | H24: Kundenservice-Spezialistin / Customer Service Specialist | I24: Customer Support | K24: ChatGPT | L24: Customer Support | M24: 1 | N24: 8 | O24: =IF(OR(M24="",N24=""),"",M24/N24) -> 0.125 | Q24: =IF(P24="","",IF(P24=0,"Free","Paid")) | R24: 4 | S24: 3 | T24: 6 | U24: 2.7 | V24: =IF(OR(U24="",M24="",M24=0),"",U24/(M24*7)) -> 0.38571429 | W24: Maybe
A25: U0141 | B25: 29 | C25: =IF(B25="","",IF(B25<18,"Under 18",IF(B25<25,"18-24",IF(B25<35,"25-34",IF(B25<45,"35-44","45+"))))) -> 25-34 | E25: United Kingdom | F25: Student | G25: High School | H25: Computer Science Student | I25: Software & IT | J25: 0 | K25: Grammarly | L25: Coding | M25: 2.6 | N25: 6.2 | O25: =IF(OR(M25="",N25=""),"",M25/N25) -> 0.41935484 | P25: 10 | Q25: =IF(P25="","",IF(P25=0,"Free","Paid")) -> Paid | R25: 3.7 | S25: 4 | T25: 7 | U25: 4.8 | V25: =IF(OR(U25="",M25="",M25=0),"",U25/(M25*7)) -> 0.26373626 | W25: Yes | Y25: Debugging Python code with AI assistants, generating boilerplate code for web projects, learning algorithms through AI-generated explanations
A26: U0205 | B26: 24 | C26: =IF(B26="","",IF(B26<18,"Under 18",IF(B26<25,"18-24",IF(B26<35,"25-34",IF(B26<45,"35-44","45+"))))) -> 18-24 | D26: Male | E26: United Kingdom | F26: Student | H26: Mechanical Engineering Student | I26: Engineering | J26: 444 | K26: Google Gemini | L26: Studying | M26: 1.2 | N26: 7.2 | O26: =IF(OR(M26="",N26=""),"",M26/N26) -> 0.16666667 | P26: 0 | Q26: =IF(P26="","",IF(P26=0,"Free","Paid")) -> Free | R26: 3.8 | S26: 3 | T26: 5 | U26: 3 | V26: =IF(OR(U26="",M26="",M26=0),"",U26/(M26*7)) -> 0.35714286 | W26: No | Y26: Analyzing complex physics problems, generating study notes from lecture content, debugging code for coursework projects, creating visual explanations of thermodynamic concepts
A27: U0209 | B27: 28 | C27: =IF(B27="","",IF(B27<18,"Under 18",IF(B27<25,"18-24",IF(B27<35,"25-34",IF(B27<45,"35-44","45+"))))) -> 25-34 | D27: Female | E27: Philippines | F27: Professional | G27: Bachelor's | H27: Digital Content Creator | I27: Content, Media & Writing | J27: 392 | K27: ChatGPT | L27: Content Creation | M27: 1.6 | N27: 7.8 | O27: =IF(OR(M27="",N27=""),"",M27/N27) -> 0.20512821 | P27: 10 | Q27: =IF(P27="","",IF(P27=0,"Free","Paid")) -> Paid | R27: 4 | S27: 2 | T27: 3 | U27: 4.5 | V27: =IF(OR(U27="",M27="",M27=0),"",U27/(M27*7)) -> 0.40178571 | W27: Yes | Y27: Generating social media captions with AI, Creating blog post drafts using language models, Editing photos and videos with AI tools, Scheduling posts across multiple platforms
A28: U0149 | B28: 23 | C28: =IF(B28="","",IF(B28<18,"Under 18",IF(B28<25,"18-24",IF(B28<35,"25-34",IF(B28<45,"35-44","45+"))))) -> 18-24 | D28: Male | E28: Brazil | F28: Student | G28: Undergraduate | H28: Computer Science Student | I28: Software & IT | J28: 215 | K28: ChatGPT | L28: Coding | M28: 0.6 | N28: 6.5 | O28: =IF(OR(M28="",N28=""),"",M28/N28) -> 0.092307692 | P28: 10 | Q28: =IF(P28="","",IF(P28=0,"Free","Paid")) -> Paid | R28: 3 | S28: 4 | T28: 5 | U28: 0 | V28: =IF(OR(U28="",M28="",M28=0),"",U28/(M28*7)) -> 0 | W28: No | Y28: Writing and debugging Python code, generating documentation for projects, optimizing algorithms
A29: U0179 | B29: 28 | C29: =IF(B29="","",IF(B29<18,"Under 18",IF(B29<25,"18-24",IF(B29<35,"25-34",IF(B29<45,"35-44","45+"))))) -> 25-34 | D29: Male | E29: Brazil | F29: Professional | G29: Bachelor's | H29: Pesquisador de Mercado | I29: Science & Research | J29: 1567 | K29: Microsoft Copilot | L29: Research | M29: 0.7 | N29: 8.1 | O29: =IF(OR(M29="",N29=""),"",M29/N29) -> 0.086419753 | P29: 0 | Q29: =IF(P29="","",IF(P29=0,"Free","Paid")) -> Free | R29: 4 | S29: 3 | T29: 6 | U29: 4.4 | V29: =IF(OR(U29="",M29="",M29=0),"",U29/(M29*7)) -> 0.89795918 | W29: No | Y29: Análise de tendências usando ferramentas de IA, extração de dados de fontes públicas, geração de relatórios automatizados, síntese de artigos acadêmicos
A30: U0016 | B30: 23 | C30: =IF(B30="","",IF(B30<18,"Under 18",IF(B30<25,"18-24",IF(B30<35,"25-34",IF(B30<45,"35-44","45+"))))) -> 18-24 | D30: Female | E30: Canada | F30: Student | G30: Undergraduate | H30: Biology Student | I30: Science & Research | K30: ChatGPT | L30: Studying | M30: 7.4 | N30: 6.8 | O30: =IF(OR(M30="",N30=""),"",M30/N30) -> 1.0882353 | P30: 0 | Q30: =IF(P30="","",IF(P30=0,"Free","Paid")) -> Free | R30: 8.7 | S30: 3 | T30: 9 | U30: 12.3 | V30: =IF(OR(U30="",M30="",M30=0),"",U30/(M30*7)) -> 0.23745174 | W30: Yes | X30: AI hrs exceed work/study hrs (kept) | Y30: Using AI to generate practice exam questions, summarizing research papers, explaining complex concepts like cellular respiration
A31: U0132 | C31: =IF(B31="","",IF(B31<18,"Under 18",IF(B31<25,"18-24",IF(B31<35,"25-34",IF(B31<45,"35-44","45+"))))) | D31: Male | E31: Australia | F31: Student | H31: Business Administration Student | I31: Business & Admin | J31: 0 | K31: ChatGPT | L31: Research | M31: 5.4 | N31: 4.8 | O31: =IF(OR(M31="",N31=""),"",M31/N31) -> 1.125 | P31: 0 | Q31: =IF(P31="","",IF(P31=0,"Free","Paid")) -> Free | R31: 7.2 | S31: 4 | T31: 8 | U31: 10.7 | V31: =IF(OR(U31="",M31="",M31=0),"",U31/(M31*7)) -> 0.28306878 | W31: No | X31: AI hrs exceed work/study hrs (kept) | Y31: Literature review and source compilation, Data analysis and statistical interpretation, Essay research and citation management
A32: U0008 | B32: 23 | C32: =IF(B32="","",IF(B32<18,"Under 18",IF(B32<25,"18-24",IF(B32<35,"25-34",IF(B32<45,"35-44","45+"))))) -> 18-24 | D32: Male | E32: Australia | F32: Student | G32: Undergraduate | H32: English Literature Student | I32: Content, Media & Writing | J32: 531 | K32: ChatGPT | L32: Writing | M32: 5.2 | N32: 7 | O32: =IF(OR(M32="",N32=""),"",M32/N32) -> 0.74285714 | P32: 0 | Q32: =IF(P32="","",IF(P32=0,"Free","Paid")) -> Free | R32: 6.7 | T32: 7 | U32: 12.1 | V32: =IF(OR(U32="",M32="",M32=0),"",U32/(M32*7)) -> 0.33241758 | W32: Yes | Y32: Essay composition and structure planning, grammar checking and proofreading, research paper summarization, creative writing feedback and editing
A33: U0162 | B33: 44 | C33: =IF(B33="","",IF(B33<18,"Under 18",IF(B33<25,"18-24",IF(B33<35,"25-34",IF(B33<45,"35-44","45+"))))) -> 35-44 | D33: Female | E33: Kenya | F33: Professional | G33: Bachelor's | H33: Research Analyst | I33: Data & Analytics | J33: 258 | K33: DeepSeek | M33: 3.7 | N33: 6.9 | O33: =IF(OR(M33="",N33=""),"",M33/N33) -> 0.53623188 | P33: 0 | Q33: =IF(P33="","",IF(P33=0,"Free","Paid")) -> Free | R33: 4.6 | S33: 5 | T33: 6 | U33: 5.7 | V33: =IF(OR(U33="",M33="",M33=0),"",U33/(M33*7)) -> 0.22007722 | W33: Yes | Y33: Literature review automation using AI databases, conducting qualitative data analysis with AI tools, generating research reports and summaries, market research data collection and synthesis
A34: U0081 | B34: 23 | C34: =IF(B34="","",IF(B34<18,"Under 18",IF(B34<25,"18-24",IF(B34<35,"25-34",IF(B34<45,"35-44","45+"))))) -> 18-24 | D34: Male | E34: Nigeria | F34: Professional | G34: Diploma | H34: Research Assistant | I34: Science & Research | J34: 334 | K34: ChatGPT | L34: Research | M34: 2.3 | N34: 7.7 | O34: =IF(OR(M34="",N34=""),"",M34/N34) -> 0.2987013 | P34: 20 | Q34: =IF(P34="","",IF(P34=0,"Free","Paid")) -> Paid | R34: 3.9 | S34: 2 | T34: 5 | U34: 2.5 | V34: =IF(OR(U34="",M34="",M34=0),"",U34/(M34*7)) -> 0.1552795 | W34: No | Y34: Literature review using AI search tools, data analysis with AI-powered statistical software, market research report generation, academic paper summarization
A35: U0014 | B35: 23 | C35: =IF(B35="","",IF(B35<18,"Under 18",IF(B35<25,"18-24",IF(B35<35,"25-34",IF(B35<45,"35-44","45+"))))) -> 18-24 | D35: Male | E35: India | F35: Student | G35: High School | H35: Engineering Student | I35: Engineering | J35: 169 | L35: Studying | M35: 5.4 | N35: 6.9 | O35: =IF(OR(M35="",N35=""),"",M35/N35) -> 0.7826087 | P35: 0 | Q35: =IF(P35="","",IF(P35=0,"Free","Paid")) -> Free | R35: 8.1 | S35: 4 | T35: 9 | U35: 6.8 | V35: =IF(OR(U35="",M35="",M35=0),"",U35/(M35*7)) -> 0.17989418 | W35: Yes | Y35: Solving physics problems with AI explanation, generating practice questions for exams, translating complex concepts into simplified notes
A36: U0278 | B36: 22 | C36: =IF(B36="","",IF(B36<18,"Under 18",IF(B36<25,"18-24",IF(B36<35,"25-34",IF(B36<45,"35-44","45+"))))) -> 18-24 | D36: Male | E36: Canada | F36: Student | G36: Undergraduate | H36: Mechanical Engineering Student | I36: Engineering | J36: 507 | K36: Perplexity AI | L36: Studying | M36: 1.9 | N36: 4.1 | O36: =IF(OR(M36="",N36=""),"",M36/N36) -> 0.46341463 | P36: 0 | Q36: =IF(P36="","",IF(P36=0,"Free","Paid")) -> Free | R36: 4.6 | S36: 3 | T36: 4 | U36: 2 | V36: =IF(OR(U36="",M36="",M36=0),"",U36/(M36*7)) -> 0.15037594 | W36: Yes | Y36: Generating practice problems and solutions for thermodynamics assignments, debugging Python code for finite element analysis projects, summarizing lecture notes on fluid mechanics concepts
A37: U0102 | B37: 18 | C37: =IF(B37="","",IF(B37<18,"Under 18",IF(B37<25,"18-24",IF(B37<35,"25-34",IF(B37<45,"35-44","45+"))))) -> 18-24 | D37: Male | E37: Philippines | F37: Student | G37: Undergraduate | H37: Information Technology Student | I37: Software & IT | J37: 0 | K37: Google Gemini | L37: Studying | M37: 1.6 | N37: 3.2 | O37: =IF(OR(M37="",N37=""),"",M37/N37) -> 0.5 | P37: 0 | Q37: =IF(P37="","",IF(P37=0,"Free","Paid")) -> Free | R37: 3.3 | S37: 4 | T37: 5 | U37: 4.3 | V37: =IF(OR(U37="",M37="",M37=0),"",U37/(M37*7)) -> 0.38392857 | W37: Yes
A38: U0258 | B38: 16 | C38: =IF(B38="","",IF(B38<18,"Under 18",IF(B38<25,"18-24",IF(B38<35,"25-34",IF(B38<45,"35-44","45+"))))) -> Under 18 | D38: Female | F38: Student | G38: Undergraduate | J38: 63 | K38: Perplexity AI | L38: Research | M38: 1.9 | N38: 5.4 | O38: =IF(OR(M38="",N38=""),"",M38/N38) -> 0.35185185 | P38: 0 | Q38: =IF(P38="","",IF(P38=0,"Free","Paid")) -> Free | R38: 3.5 | S38: 3 | T38: 5 | U38: 3 | V38: =IF(OR(U38="",M38="",M38=0),"",U38/(M38*7)) -> 0.22556391 | W38: Maybe | Y38: Literature review and paper summarization, Data analysis and interpretation, Research proposal drafting, Scientific article finding and organization
A39: U0239 | B39: 45 | C39: =IF(B39="","",IF(B39<18,"Under 18",IF(B39<25,"18-24",IF(B39<35,"25-34",IF(B39<45,"35-44","45+"))))) -> 45+ | D39: Male | E39: Pakistan | F39: Professional | G39: Master's | H39: Senior Software Engineer | I39: Software & IT | J39: 887 | L39: Coding | M39: 1.5 | N39: 6.4 | O39: =IF(OR(M39="",N39=""),"",M39/N39) -> 0.234375 | P39: 0 | Q39: =IF(P39="","",IF(P39=0,"Free","Paid")) -> Free | R39: 5.3 | S39: 3 | T39: 5 | U39: 5.3 | V39: =IF(OR(U39="",M39="",M39=0),"",U39/(M39*7)) -> 0.5047619 | W39: Maybe | Y39: Code review and optimization using AI assistants, automated bug detection and debugging with AI tools, AI-assisted documentation generation, infrastructure code maintenance
A40: U0071 | B40: 30 | C40: =IF(B40="","",IF(B40<18,"Under 18",IF(B40<25,"18-24",IF(B40<35,"25-34",IF(B40<45,"35-44","45+"))))) -> 25-34 | E40: India | F40: Professional | G40: Master's | H40: Data Analytics Manager | I40: Data & Analytics | J40: 1699 | K40: Perplexity AI | L40: Data Analysis | M40: 5.5 | N40: 7.5 | O40: =IF(OR(M40="",N40=""),"",M40/N40) -> 0.73333333 | P40: 10 | Q40: =IF(P40="","",IF(P40=0,"Free","Paid")) -> Paid | S40: 4 | T40: 8 | U40: 6.5 | V40: =IF(OR(U40="",M40="",M40=0),"",U40/(M40*7)) -> 0.16883117 | W40: Yes | Y40: Building predictive models with Python and scikit-learn, Creating business intelligence dashboards in Tableau, Performing statistical analysis on customer datasets
A41: U0259 | B41: 43 | C41: =IF(B41="","",IF(B41<18,"Under 18",IF(B41<25,"18-24",IF(B41<35,"25-34",IF(B41<45,"35-44","45+"))))) -> 35-44 | D41: Male | E41: Brazil | F41: Professional | G41: PhD | H41: Engenheiro de Software Sênior / Tech Lead | I41: Software & IT | K41: ChatGPT | L41: Coding | M41: 0.6 | N41: 10.1 | O41: =IF(OR(M41="",N41=""),"",M41/N41) -> 0.059405941 | P41: 20 | Q41: =IF(P41="","",IF(P41=0,"Free","Paid")) -> Paid | R41: 4 | S41: 2 | T41: 5 | U41: 0 | V41: =IF(OR(U41="",M41="",M41=0),"",U41/(M41*7)) -> 0 | W41: Maybe | Y41: Desenvolvimento de algoritmos com assistência de IA, code review automatizado com ferramentas de IA, arquitetura de sistemas de software, mentoria de equipes em práticas de desenvolvimento com IA
A42: U0075 | B42: 29 | C42: =IF(B42="","",IF(B42<18,"Under 18",IF(B42<25,"18-24",IF(B42<35,"25-34",IF(B42<45,"35-44","45+"))))) -> 25-34 | D42: Male | E42: United States | F42: Professional | G42: Bachelor's | H42: Content Writer | I42: Content, Media & Writing | J42: 5260 | K42: ChatGPT | L42: Writing | M42: 1.6 | N42: 6.7 | O42: =IF(OR(M42="",N42=""),"",M42/N42) -> 0.23880597 | P42: 0 | Q42: =IF(P42="","",IF(P42=0,"Free","Paid")) -> Free | R42: 3.9 | S42: 4 | T42: 5 | U42: 5.2 | V42: =IF(OR(U42="",M42="",M42=0),"",U42/(M42*7)) -> 0.46428571 | Y42: Drafting blog posts and articles with AI writing assistants, using AI tools to brainstorm content ideas and outline structures, editing and refining generated content for tone and accuracy
A43: U0288 | B43: 36 | C43: =IF(B43="","",IF(B43<18,"Under 18",IF(B43<25,"18-24",IF(B43<35,"25-34",IF(B43<45,"35-44","45+"))))) -> 35-44 | D43: Male | E43: Pakistan | F43: Professional | G43: Master's | H43: Senior Software Engineer / Technical Lead | I43: Software & IT | J43: 513 | K43: ChatGPT | L43: Coding | M43: 3.7 | N43: 10.1 | O43: =IF(OR(M43="",N43=""),"",M43/N43) -> 0.36633663 | P43: 0 | Q43: =IF(P43="","",IF(P43=0,"Free","Paid")) -> Free | R43: 5.7 | S43: 2 | T43: 5 | U43: 5.8 | V43: =IF(OR(U43="",M43="",M43=0),"",U43/(M43*7)) -> 0.22393822 | W43: Maybe | Y43: Code generation and debugging using AI, automated code review and optimization, rapid prototyping using AI-assisted development frameworks, API design and documentation using AI tools
A44: U0271 | B44: 24 | C44: =IF(B44="","",IF(B44<18,"Under 18",IF(B44<25,"18-24",IF(B44<35,"25-34",IF(B44<45,"35-44","45+"))))) -> 18-24 | D44: Female | E44: India | F44: Professional | G44: Bachelor's | H44: Software Developer | I44: Software & IT | J44: 2307 | K44: Grammarly | L44: Coding | M44: 0.6 | N44: 12 | O44: =IF(OR(M44="",N44=""),"",M44/N44) -> 0.05 | P44: 0 | Q44: =IF(P44="","",IF(P44=0,"Free","Paid")) -> Free | R44: 4.4 | S44: 4 | T44: 7 | U44: 1.6 | V44: =IF(OR(U44="",M44="",M44=0),"",U44/(M44*7)) -> 0.38095238 | W44: Yes | Y44: Code debugging and optimization using AI assistants, automated test case generation, API integration and documentation, algorithm optimization suggestions
A45: U0070 | B45: 17 | C45: =IF(B45="","",IF(B45<18,"Under 18",IF(B45<25,"18-24",IF(B45<35,"25-34",IF(B45<45,"35-44","45+"))))) -> Under 18 | E45: Brazil | F45: Student | G45: Undergraduate | J45: 234 | K45: ChatGPT | L45: Studying | M45: 5.1 | N45: 7.2 | O45: =IF(OR(M45="",N45=""),"",M45/N45) -> 0.70833333 | P45: 0 | Q45: =IF(P45="","",IF(P45=0,"Free","Paid")) -> Free | R45: 8.3 | S45: 5 | T45: 9 | U45: 11.4 | V45: =IF(OR(U45="",M45="",M45=0),"",U45/(M45*7)) -> 0.31932773 | W45: Yes | Y45: Using AI to solve physics problems, generating study summaries for calculus, translating technical documents from English to Portuguese
A46: U0054 | B46: 20 | C46: =IF(B46="","",IF(B46<18,"Under 18",IF(B46<25,"18-24",IF(B46<35,"25-34",IF(B46<45,"35-44","45+"))))) -> 18-24 | D46: Male | E46: India | F46: Student | G46: High School | H46: Computer Science Student | I46: Software & IT | J46: 206 | K46: Google Gemini | L46: Coding | M46: 2.4 | N46: 8.6 | O46: =IF(OR(M46="",N46=""),"",M46/N46) -> 0.27906977 | P46: 20 | Q46: =IF(P46="","",IF(P46=0,"Free","Paid")) -> Paid | R46: 5.5 | S46: 3 | T46: 5 | U46: 7.3 | V46: =IF(OR(U46="",M46="",M46=0),"",U46/(M46*7)) -> 0.43452381 | W46: Yes | Y46: Debugging code with AI assistants, Learning Python and JavaScript syntax, Solving LeetCode problems with AI explanations
A47: U0164 | B47: 44 | C47: =IF(B47="","",IF(B47<18,"Under 18",IF(B47<25,"18-24",IF(B47<35,"25-34",IF(B47<45,"35-44","45+"))))) -> 35-44 | D47: Female | E47: Nigeria | F47: Professional | G47: Master's | H47: Research Scientist/Senior Research Officer | I47: Science & Research | J47: 384 | K47: Microsoft Copilot | L47: Research | M47: 0.9 | N47: 7.9 | O47: =IF(OR(M47="",N47=""),"",M47/N47) -> 0.11392405 | P47: 10 | Q47: =IF(P47="","",IF(P47=0,"Free","Paid")) -> Paid | R47: 3.1 | S47: 3 | T47: 4 | U47: 1.2 | V47: =IF(OR(U47="",M47="",M47=0),"",U47/(M47*7)) -> 0.19047619 | W47: No | Y47: Literature review automation with AI tools, data analysis and pattern recognition, research paper synthesis and summarization, hypothesis validation using machine learning models
A48: U0219 | B48: 21 | C48: =IF(B48="","",IF(B48<18,"Under 18",IF(B48<25,"18-24",IF(B48<35,"25-34",IF(B48<45,"35-44","45+"))))) -> 18-24 | D48: Male | E48: United Kingdom | F48: Student | G48: Master's | H48: Artificial Intelligence and Machine Learning Student | I48: Software & IT | J48: 206 | K48: Google Gemini | L48: Coding | M48: 9.1 | N48: 5.4 | O48: =IF(OR(M48="",N48=""),"",M48/N48) -> 1.6851852 | P48: 30 | Q48: =IF(P48="","",IF(P48=0,"Free","Paid")) -> Paid | R48: 6.5 | S48: 3 | T48: 8 | U48: 14.9 | V48: =IF(OR(U48="",M48="",M48=0),"",U48/(M48*7)) -> 0.23390895 | W48: Yes | X48: AI hrs exceed work/study hrs (kept) | Y48: Debugging Python code with AI-powered IDE plugins, Generating optimization algorithms for data structures, Writing and testing unit tests for complex modules
A49: U0036 | B49: 34 | C49: =IF(B49="","",IF(B49<18,"Under 18",IF(B49<25,"18-24",IF(B49<35,"25-34",IF(B49<45,"35-44","45+"))))) -> 25-34 | D49: Female | E49: United States | F49: Professional | G49: Master's | H49: Content Strategy Manager | I49: Content, Media & Writing | J49: 5669 | K49: ChatGPT | L49: Writing | M49: 8 | N49: 7.4 | O49: =IF(OR(M49="",N49=""),"",M49/N49) -> 1.0810811 | P49: 0 | Q49: =IF(P49="","",IF(P49=0,"Free","Paid")) -> Free | R49: 7.3 | S49: 2 | T49: 7 | U49: 16.3 | V49: =IF(OR(U49="",M49="",M49=0),"",U49/(M49*7)) -> 0.29107143 | W49: Yes | X49: AI hrs exceed work/study hrs (kept) | Y49: Uses AI tools to generate initial content drafts, optimize SEO metadata and headlines, streamline editing and proofreading processes, manage multi-channel content calendars
A50: U0057 | B50: 18 | C50: =IF(B50="","",IF(B50<18,"Under 18",IF(B50<25,"18-24",IF(B50<35,"25-34",IF(B50<45,"35-44","45+"))))) -> 18-24 | D50: Male | E50: Philippines | F50: Student | G50: High School | H50: English Literature Student | I50: Content, Media & Writing | J50: 198 | K50: Perplexity AI | L50: Writing | N50: 7.2 | O50: =IF(OR(M50="",N50=""),"",M50/N50) | P50: 0 | Q50: =IF(P50="","",IF(P50=0,"Free","Paid")) -> Free | R50: 6.9 | S50: 2 | T50: 6 | U50: 7.2 | V50: =IF(OR(U50="",M50="",M50=0),"",U50/(M50*7)) | W50: Maybe | Y50: Essay composition and structure planning, grammar and spelling correction, brainstorming ideas for creative writing assignments
A51: U0060 | C51: =IF(B51="","",IF(B51<18,"Under 18",IF(B51<25,"18-24",IF(B51<35,"25-34",IF(B51<45,"35-44","45+"))))) | D51: Female | E51: Philippines | F51: Student | G51: Bachelor's | J51: 190 | K51: ChatGPT | L51: Research | M51: 7.7 | N51: 6.8 | O51: =IF(OR(M51="",N51=""),"",M51/N51) -> 1.1323529 | Q51: =IF(P51="","",IF(P51=0,"Free","Paid")) | R51: 8.4 | S51: 5 | T51: 10 | U51: 13.6 | V51: =IF(OR(U51="",M51="",M51=0),"",U51/(M51*7)) -> 0.25231911 | W51: Yes | X51: AI hrs exceed work/study hrs (kept) | Y51: Literature review and paper summarization, Data analysis for research datasets, Academic paper organization and citation management
A52: U0226 | B52: 32 | C52: =IF(B52="","",IF(B52<18,"Under 18",IF(B52<25,"18-24",IF(B52<35,"25-34",IF(B52<45,"35-44","45+"))))) -> 25-34 | D52: Male | E52: Nigeria | F52: Professional | G52: High School | H52: Social Media Content Creator / Digital Marketer | I52: Content, Media & Writing | J52: 376 | K52: Claude | L52: Content Creation | M52: 1.3 | N52: 11.6 | O52: =IF(OR(M52="",N52=""),"",M52/N52) -> 0.11206897 | P52: 20 | Q52: =IF(P52="","",IF(P52=0,"Free","Paid")) -> Paid | R52: 3.3 | S52: 4 | T52: 5 | U52: 3.2 | V52: =IF(OR(U52="",M52="",M52=0),"",U52/(M52*7)) -> 0.35164835 | W52: Maybe | Y52: Creating engaging social media posts with AI writing tools, Generating captions and hashtags using AI, Editing and optimizing images with AI-powered design tools, Producing video content summaries and descriptions
A53: U0118 | B53: 44 | C53: =IF(B53="","",IF(B53<18,"Under 18",IF(B53<25,"18-24",IF(B53<35,"25-34",IF(B53<45,"35-44","45+"))))) -> 35-44 | D53: Other / Non-binary | E53: France | F53: Professional | G53: Bachelor's | H53: Responsable de Contenu Digital | I53: Content, Media & Writing | J53: 3477 | K53: ChatGPT | L53: Content Creation | M53: 2.2 | N53: 10.7 | O53: =IF(OR(M53="",N53=""),"",M53/N53) -> 0.20560748 | P53: 0 | Q53: =IF(P53="","",IF(P53=0,"Free","Paid")) -> Free | R53: 5 | S53: 4 | U53: 2.8 | V53: =IF(OR(U53="",M53="",M53=0),"",U53/(M53*7)) -> 0.18181818 | W53: Yes | Y53: Création d'articles de blog avec assistance IA, Génération de contenu pour réseaux sociaux, Optimisation SEO avec outils IA, Édition et révision de textes
A54: U0028 | C54: =IF(B54="","",IF(B54<18,"Under 18",IF(B54<25,"18-24",IF(B54<35,"25-34",IF(B54<45,"35-44","45+"))))) | D54: Other / Non-binary | E54: Pakistan | F54: Student | G54: Undergraduate | H54: English Literature Student | I54: Content, Media & Writing | J54: 100 | K54: ChatGPT | L54: Writing | M54: 1.2 | N54: 5.7 | O54: =IF(OR(M54="",N54=""),"",M54/N54) -> 0.21052632 | P54: 50 | Q54: =IF(P54="","",IF(P54=0,"Free","Paid")) -> Paid | R54: 5.8 | S54: 4 | T54: 7 | V54: =IF(OR(U54="",M54="",M54=0),"",U54/(M54*7)) | W54: Yes | Y54: Essay drafting and outline generation, academic paper research summarization, creative writing feedback and editing
A55: U0125 | B55: 26 | C55: =IF(B55="","",IF(B55<18,"Under 18",IF(B55<25,"18-24",IF(B55<35,"25-34",IF(B55<45,"35-44","45+"))))) -> 25-34 | E55: Nigeria | F55: Student | G55: High School | H55: Computer Science Student | I55: Software & IT | J55: 0 | K55: ChatGPT | L55: Coding | M55: 0.6 | N55: 8.8 | O55: =IF(OR(M55="",N55=""),"",M55/N55) -> 0.068181818 | P55: 0 | Q55: =IF(P55="","",IF(P55=0,"Free","Paid")) -> Free | R55: 3.2 | S55: 2 | T55: 5 | U55: 2.2 | V55: =IF(OR(U55="",M55="",M55=0),"",U55/(M55*7)) -> 0.52380952 | W55: Yes | Y55: Debugging Python code with AI code analysis, Writing SQL queries for database projects, Generating HTML/CSS templates for web assignments
A56: U0223 | B56: 33 | C56: =IF(B56="","",IF(B56<18,"Under 18",IF(B56<25,"18-24",IF(B56<35,"25-34",IF(B56<45,"35-44","45+"))))) -> 25-34 | D56: Female | E56: Australia | F56: Professional | G56: Diploma | H56: Marketing Communications Officer | I56: Content, Media & Writing | J56: 6197 | K56: ChatGPT | L56: Writing | M56: 1.9 | N56: 11 | O56: =IF(OR(M56="",N56=""),"",M56/N56) -> 0.17272727 | Q56: =IF(P56="","",IF(P56=0,"Free","Paid")) | R56: 5.4 | S56: 4 | T56: 7 | U56: 6 | V56: =IF(OR(U56="",M56="",M56=0),"",U56/(M56*7)) -> 0.45112782 | W56: Yes | Y56: AI-assisted content writing for social media and marketing campaigns, proofreading and editing copy with AI grammar tools, generating email newsletters and promotional materials
A57: U0243 | B57: 31 | C57: =IF(B57="","",IF(B57<18,"Under 18",IF(B57<25,"18-24",IF(B57<35,"25-34",IF(B57<45,"35-44","45+"))))) -> 25-34 | D57: Male | E57: Australia | F57: Professional | G57: Bachelor's | H57: Customer Support Specialist | I57: Customer Support | J57: 5355 | K57: Google Gemini | L57: Customer Support | M57: 4.6 | N57: 8.7 | O57: =IF(OR(M57="",N57=""),"",M57/N57) -> 0.52873563 | P57: 0 | Q57: =IF(P57="","",IF(P57=0,"Free","Paid")) -> Free | R57: 8.8 | S57: 2 | T57: 6 | U57: 11.5 | V57: =IF(OR(U57="",M57="",M57=0),"",U57/(M57*7)) -> 0.35714286 | W57: Yes | Y57: Drafting customer responses using AI writing assistants, analyzing customer feedback with sentiment analysis tools, resolving FAQs using AI knowledge base systems, escalating complex issues to senior staff
A58: U0165 | B58: 22 | C58: =IF(B58="","",IF(B58<18,"Under 18",IF(B58<25,"18-24",IF(B58<35,"25-34",IF(B58<45,"35-44","45+"))))) -> 18-24 | D58: Male | E58: Brazil | F58: Student | G58: High School | H58: Mechanical Engineering Student | I58: Engineering | J58: 86 | K58: Google Gemini | L58: Studying | M58: 1.4 | O58: =IF(OR(M58="",N58=""),"",M58/N58) | P58: 0 | Q58: =IF(P58="","",IF(P58=0,"Free","Paid")) -> Free | R58: 1.9 | S58: 3 | T58: 5 | U58: 1.7 | V58: =IF(OR(U58="",M58="",M58=0),"",U58/(M58*7)) -> 0.17346939 | W58: Yes | Y58: Using AI to solve physics and calculus problems, generating practice exam questions, translating technical documentation from English to Portuguese
A59: U0238 | B59: 21 | C59: =IF(B59="","",IF(B59<18,"Under 18",IF(B59<25,"18-24",IF(B59<35,"25-34",IF(B59<45,"35-44","45+"))))) -> 18-24 | D59: Male | E59: Pakistan | F59: Student | G59: High School | H59: Digital Media Student | I59: Content, Media & Writing | J59: 62 | K59: ChatGPT | L59: Content Creation | M59: 7.2 | N59: 6.1 | O59: =IF(OR(M59="",N59=""),"",M59/N59) -> 1.1803279 | P59: 10 | Q59: =IF(P59="","",IF(P59=0,"Free","Paid")) -> Paid | R59: 6.8 | S59: 4 | T59: 7 | U59: 13.2 | V59: =IF(OR(U59="",M59="",M59=0),"",U59/(M59*7)) -> 0.26190476 | W59: Yes | X59: AI hrs exceed work/study hrs (kept) | Y59: Creating social media graphics with AI design tools, Writing blog posts and articles with AI writing assistants, Generating video scripts and editing content with AI video tools
A60: U0069 | B60: 32 | C60: =IF(B60="","",IF(B60<18,"Under 18",IF(B60<25,"18-24",IF(B60<35,"25-34",IF(B60<45,"35-44","45+"))))) -> 25-34 | D60: Male | E60: Canada | F60: Professional | G60: Bachelor's | H60: Content Marketing Manager | I60: Content, Media & Writing | J60: 3337 | K60: ChatGPT | M60: 1.3 | N60: 7.6 | O60: =IF(OR(M60="",N60=""),"",M60/N60) -> 0.17105263 | P60: 0 | Q60: =IF(P60="","",IF(P60=0,"Free","Paid")) -> Free | R60: 3.8 | S60: 4 | T60: 7 | U60: 2.9 | V60: =IF(OR(U60="",M60="",M60=0),"",U60/(M60*7)) -> 0.31868132 | W60: Yes | Y60: Creating blog posts and web copy with AI writing assistants, editing and refining client proposals, generating social media content calendars and posts
A61: U0092 | B61: 22 | C61: =IF(B61="","",IF(B61<18,"Under 18",IF(B61<25,"18-24",IF(B61<35,"25-34",IF(B61<45,"35-44","45+"))))) -> 18-24 | D61: Male | E61: Pakistan | F61: Student | G61: Bachelor's | H61: Computer Science Student | I61: Software & IT | J61: 113 | K61: Perplexity AI | L61: Data Analysis | M61: 1 | N61: 6.5 | O61: =IF(OR(M61="",N61=""),"",M61/N61) -> 0.15384615 | P61: 0 | Q61: =IF(P61="","",IF(P61=0,"Free","Paid")) -> Free | R61: 3.2 | S61: 3 | T61: 3 | U61: 4.2 | V61: =IF(OR(U61="",M61="",M61=0),"",U61/(M61*7)) -> 0.6 | W61: No | Y61: Statistical analysis of datasets, data visualization using Python libraries, predictive modeling with machine learning algorithms, database query optimization
A62: U0043 | B62: 21 | C62: =IF(B62="","",IF(B62<18,"Under 18",IF(B62<25,"18-24",IF(B62<35,"25-34",IF(B62<45,"35-44","45+"))))) -> 18-24 | D62: Male | E62: United Kingdom | F62: Student | G62: Undergraduate | H62: Computer Science Student | I62: Software & IT | J62: 118 | K62: Google Gemini | L62: Coding | N62: 6.3 | O62: =IF(OR(M62="",N62=""),"",M62/N62) | P62: 0 | Q62: =IF(P62="","",IF(P62=0,"Free","Paid")) -> Free | R62: 7.6 | S62: 2 | T62: 6 | U62: 12.4 | V62: =IF(OR(U62="",M62="",M62=0),"",U62/(M62*7)) | W62: Yes
A63: U0084 | B63: 47 | C63: =IF(B63="","",IF(B63<18,"Under 18",IF(B63<25,"18-24",IF(B63<35,"25-34",IF(B63<45,"35-44","45+"))))) -> 45+ | D63: Male | E63: Nigeria | F63: Professional | G63: Bachelor's | H63: Business Intelligence Analyst | I63: Data & Analytics | J63: 1104 | K63: Grammarly | L63: Data Analysis | M63: 3.4 | N63: 7.3 | O63: =IF(OR(M63="",N63=""),"",M63/N63) -> 0.46575342 | P63: 20 | Q63: =IF(P63="","",IF(P63=0,"Free","Paid")) -> Paid | R63: 4.9 | S63: 3 | T63: 5 | U63: 7.4 | V63: =IF(OR(U63="",M63="",M63=0),"",U63/(M63*7)) -> 0.31092437 | W63: No | Y63: Cleaning and processing customer transaction data, generating sales trend reports using Python, creating data visualizations in Power BI dashboards
A64: U0061 | B64: 33 | C64: =IF(B64="","",IF(B64<18,"Under 18",IF(B64<25,"18-24",IF(B64<35,"25-34",IF(B64<45,"35-44","45+"))))) -> 25-34 | D64: Male | E64: Brazil | F64: Professional | G64: Bachelor's | H64: Desenvolvedor de Software Sênior | I64: Software & IT | J64: 552 | K64: Google Gemini | L64: Coding | M64: 0.5 | N64: 10.2 | O64: =IF(OR(M64="",N64=""),"",M64/N64) -> 0.049019608 | P64: 20 | Q64: =IF(P64="","",IF(P64=0,"Free","Paid")) -> Paid | R64: 2.9 | S64: 3 | T64: 5 | U64: 0.1 | V64: =IF(OR(U64="",M64="",M64=0),"",U64/(M64*7)) -> 0.028571429 | W64: No | Y64: Usar GitHub Copilot para completar código, gerar testes unitários com IA, otimizar algoritmos com sugestões de IA, revisar e debugar código com assistentes de IA
A65: U0116 | B65: 20 | C65: =IF(B65="","",IF(B65<18,"Under 18",IF(B65<25,"18-24",IF(B65<35,"25-34",IF(B65<45,"35-44","45+"))))) -> 18-24 | D65: Male | E65: India | F65: Student | G65: Undergraduate | H65: Digital Media and Communications Student | I65: Content, Media & Writing | J65: 79 | K65: Google Gemini | L65: Content Creation | M65: 3.5 | N65: 6.2 | O65: =IF(OR(M65="",N65=""),"",M65/N65) -> 0.56451613 | P65: 20 | Q65: =IF(P65="","",IF(P65=0,"Free","Paid")) -> Paid | R65: 4.7 | S65: 4 | T65: 7 | U65: 8.3 | V65: =IF(OR(U65="",M65="",M65=0),"",U65/(M65*7)) -> 0.33877551 | W65: Yes | Y65: AI-assisted blog writing and SEO optimization, video scriptwriting and thumbnail design generation, social media content creation and caption generation
A66: U0039 | B66: 23 | C66: =IF(B66="","",IF(B66<18,"Under 18",IF(B66<25,"18-24",IF(B66<35,"25-34",IF(B66<45,"35-44","45+"))))) -> 18-24 | D66: Male | E66: United Kingdom | F66: Student | G66: Master's | H66: Bioinformatics Student | I66: Science & Research | J66: 614 | K66: Claude | L66: Research | M66: 1 | N66: 6.6 | O66: =IF(OR(M66="",N66=""),"",M66/N66) -> 0.15151515 | P66: 20 | Q66: =IF(P66="","",IF(P66=0,"Free","Paid")) -> Paid | R66: 2.5 | S66: 4 | T66: 6 | U66: 0.7 | V66: =IF(OR(U66="",M66="",M66=0),"",U66/(M66*7)) -> 0.1 | W66: Maybe | Y66: Literature review automation with AI summarization, designing research methodology frameworks, analyzing genomic datasets using machine learning models, peer review preparation assistance
A67: U0022 | B67: 37 | C67: =IF(B67="","",IF(B67<18,"Under 18",IF(B67<25,"18-24",IF(B67<35,"25-34",IF(B67<45,"35-44","45+"))))) -> 35-44 | D67: Female | E67: India | F67: Professional | G67: Diploma | H67: Software Developer | I67: Software & IT | J67: 1404 | K67: ChatGPT | L67: Coding | M67: 1.7 | N67: 6.4 | O67: =IF(OR(M67="",N67=""),"",M67/N67) -> 0.265625 | Q67: =IF(P67="","",IF(P67=0,"Free","Paid")) | R67: 5.7 | S67: 5 | T67: 7 | U67: 3.4 | V67: =IF(OR(U67="",M67="",M67=0),"",U67/(M67*7)) -> 0.28571429 | W67: Yes | Y67: Writing and debugging Python code using AI assistants, automating repetitive coding tasks with AI tools, code review and optimization with AI-powered suggestions
A68: U0137 | B68: 23 | C68: =IF(B68="","",IF(B68<18,"Under 18",IF(B68<25,"18-24",IF(B68<35,"25-34",IF(B68<45,"35-44","45+"))))) -> 18-24 | D68: Other / Non-binary | F68: Student | G68: Master's | H68: Software Engineering Student | I68: Software & IT | J68: 0 | K68: Microsoft Copilot | L68: Coding | M68: 1 | N68: 6.2 | O68: =IF(OR(M68="",N68=""),"",M68/N68) -> 0.16129032 | P68: 20 | Q68: =IF(P68="","",IF(P68=0,"Free","Paid")) -> Paid | R68: 3.3 | S68: 3 | T68: 5 | U68: 2.6 | V68: =IF(OR(U68="",M68="",M68=0),"",U68/(M68*7)) -> 0.37142857 | W68: Yes | Y68: Code debugging and optimization, API development and integration, machine learning model training and implementation
A69: U0027 | B69: 20 | C69: =IF(B69="","",IF(B69<18,"Under 18",IF(B69<25,"18-24",IF(B69<35,"25-34",IF(B69<45,"35-44","45+"))))) -> 18-24 | D69: Male | E69: United Kingdom | F69: Student | G69: Undergraduate | H69: Computer Science Student | I69: Software & IT | J69: 0 | K69: ChatGPT | L69: Coding | M69: 1.3 | N69: 8.1 | O69: =IF(OR(M69="",N69=""),"",M69/N69) -> 0.16049383 | P69: 0 | Q69: =IF(P69="","",IF(P69=0,"Free","Paid")) -> Free | R69: 4.8 | S69: 4 | T69: 7 | U69: 2.9 | V69: =IF(OR(U69="",M69="",M69=0),"",U69/(M69*7)) -> 0.31868132 | W69: Yes | Y69: Debugging code with AI assistance, generating boilerplate code for projects, learning new programming concepts through AI explanations
A70: U0268 | B70: 31 | C70: =IF(B70="","",IF(B70<18,"Under 18",IF(B70<25,"18-24",IF(B70<35,"25-34",IF(B70<45,"35-44","45+"))))) -> 25-34 | D70: Female | E70: France | F70: Student | G70: Undergraduate | H70: Biology Student | I70: Science & Research | J70: 302 | K70: Google Gemini | L70: Studying | M70: 0.7 | N70: 4.5 | O70: =IF(OR(M70="",N70=""),"",M70/N70) -> 0.15555556 | P70: 0 | Q70: =IF(P70="","",IF(P70=0,"Free","Paid")) -> Free | R70: 3.4 | T70: 5 | U70: 0.8 | V70: =IF(OR(U70="",M70="",M70=0),"",U70/(M70*7)) -> 0.16326531 | W70: Maybe | Y70: Using AI to generate study summaries, practice exam questions, and lab report writing assistance
A71: U0131 | B71: 35 | C71: =IF(B71="","",IF(B71<18,"Under 18",IF(B71<25,"18-24",IF(B71<35,"25-34",IF(B71<45,"35-44","45+"))))) -> 35-44 | E71: United States | F71: Professional | G71: Diploma | H71: Administrative Assistant | I71: Business & Admin | J71: 5966 | K71: ChatGPT | L71: Office Work | M71: 4.9 | N71: 9.3 | O71: =IF(OR(M71="",N71=""),"",M71/N71) -> 0.52688172 | P71: 20 | Q71: =IF(P71="","",IF(P71=0,"Free","Paid")) -> Paid | R71: 5.7 | S71: 3 | T71: 5 | U71: 11.5 | V71: =IF(OR(U71="",M71="",M71=0),"",U71/(M71*7)) -> 0.33527697 | W71: Yes | Y71: Data entry and document formatting with AI tools, scheduling meetings and managing calendar using AI assistants, generating business reports with AI summarization software, proofreading emails and correspondence using grammar AI
A72: U0255 | B72: 28 | C72: =IF(B72="","",IF(B72<18,"Under 18",IF(B72<25,"18-24",IF(B72<35,"25-34",IF(B72<45,"35-44","45+"))))) -> 25-34 | D72: Male | E72: Australia | F72: Professional | G72: Master's | H72: Senior Software Engineer | I72: Software & IT | J72: 3610 | K72: Google Gemini | L72: Coding | M72: 4.3 | N72: 8.1 | O72: =IF(OR(M72="",N72=""),"",M72/N72) -> 0.5308642 | P72: 0 | Q72: =IF(P72="","",IF(P72=0,"Free","Paid")) -> Free | R72: 6.1 | S72: 3 | T72: 7 | U72: 6.7 | V72: =IF(OR(U72="",M72="",M72=0),"",U72/(M72*7)) -> 0.22259136 | W72: Yes | Y72: Code generation and debugging with AI assistants, automated testing and deployment pipeline optimization, machine learning model implementation and optimization
A73: U0231 | B73: 22 | C73: =IF(B73="","",IF(B73<18,"Under 18",IF(B73<25,"18-24",IF(B73<35,"25-34",IF(B73<45,"35-44","45+"))))) -> 18-24 | D73: Male | E73: Nigeria | F73: Professional | G73: Master's | H73: Data Analyst | I73: Data & Analytics | J73: 1091 | L73: Data Analysis | M73: 2.4 | N73: 8 | O73: =IF(OR(M73="",N73=""),"",M73/N73) -> 0.3 | P73: 0 | Q73: =IF(P73="","",IF(P73=0,"Free","Paid")) -> Free | R73: 5.4 | S73: 4 | T73: 5 | U73: 2.6 | V73: =IF(OR(U73="",M73="",M73=0),"",U73/(M73*7)) -> 0.1547619 | W73: Yes | Y73: Building predictive models with machine learning algorithms, Creating automated dashboards for business intelligence, Cleaning and transforming large datasets for analysis
A74: U0067 | B74: 22 | C74: =IF(B74="","",IF(B74<18,"Under 18",IF(B74<25,"18-24",IF(B74<35,"25-34",IF(B74<45,"35-44","45+"))))) -> 18-24 | D74: Other / Non-binary | E74: India | F74: Student | G74: Undergraduate | H74: Biotechnology Student | I74: Science & Research | J74: 68 | K74: ChatGPT | M74: 0.7 | N74: 8.6 | O74: =IF(OR(M74="",N74=""),"",M74/N74) -> 0.081395349 | P74: 0 | Q74: =IF(P74="","",IF(P74=0,"Free","Paid")) -> Free | R74: 4.1 | S74: 4 | T74: 6 | U74: 2.1 | V74: =IF(OR(U74="",M74="",M74=0),"",U74/(M74*7)) -> 0.42857143 | W74: No | Y74: Literature review automation, research paper summarization, data analysis and visualization, hypothesis generation
A75: U0234 | C75: =IF(B75="","",IF(B75<18,"Under 18",IF(B75<25,"18-24",IF(B75<35,"25-34",IF(B75<45,"35-44","45+"))))) | D75: Female | E75: Nigeria | F75: Student | G75: Bachelor's | H75: English Literature Student | I75: Content, Media & Writing | K75: ChatGPT | L75: Writing | M75: 2.1 | N75: 5.9 | O75: =IF(OR(M75="",N75=""),"",M75/N75) -> 0.3559322 | P75: 0 | Q75: =IF(P75="","",IF(P75=0,"Free","Paid")) -> Free | R75: 4.7 | S75: 5 | T75: 8 | V75: =IF(OR(U75="",M75="",M75=0),"",U75/(M75*7)) | W75: Yes | Y75: Essay composition and structure planning, grammar and style checking, research paper organization, content brainstorming for creative writing assignments
A76: U0184 | B76: 36 | C76: =IF(B76="","",IF(B76<18,"Under 18",IF(B76<25,"18-24",IF(B76<35,"25-34",IF(B76<45,"35-44","45+"))))) -> 35-44 | D76: Female | E76: Philippines | F76: Professional | G76: PhD | H76: Senior Software Engineer / AI Solutions Architect | I76: Software & IT | J76: 1378 | K76: Perplexity AI | L76: Coding | M76: 2.1 | N76: 7.8 | O76: =IF(OR(M76="",N76=""),"",M76/N76) -> 0.26923077 | P76: 0 | Q76: =IF(P76="","",IF(P76=0,"Free","Paid")) -> Free | R76: 3.8 | S76: 4 | T76: 5 | U76: 2.8 | V76: =IF(OR(U76="",M76="",M76=0),"",U76/(M76*7)) -> 0.19047619 | W76: Yes
A77: U0096 | B77: 17 | C77: =IF(B77="","",IF(B77<18,"Under 18",IF(B77<25,"18-24",IF(B77<35,"25-34",IF(B77<45,"35-44","45+"))))) -> Under 18 | D77: Male | E77: United States | F77: Student | G77: High School | H77: Environmental Science Student | I77: Science & Research | J77: 884 | L77: Research | M77: 7 | N77: 5.8 | O77: =IF(OR(M77="",N77=""),"",M77/N77) -> 1.2068966 | P77: 20 | Q77: =IF(P77="","",IF(P77=0,"Free","Paid")) -> Paid | R77: 9.7 | S77: 4 | T77: 10 | U77: 12.8 | V77: =IF(OR(U77="",M77="",M77=0),"",U77/(M77*7)) -> 0.26122449 | W77: Yes | X77: AI hrs exceed work/study hrs (kept)
A78: U0274 | B78: 39 | C78: =IF(B78="","",IF(B78<18,"Under 18",IF(B78<25,"18-24",IF(B78<35,"25-34",IF(B78<45,"35-44","45+"))))) -> 35-44 | D78: Female | E78: United States | F78: Professional | G78: Bachelor's | H78: Data Analyst | I78: Data & Analytics | J78: 3204 | K78: ChatGPT | L78: Data Analysis | M78: 2.6 | N78: 9.2 | O78: =IF(OR(M78="",N78=""),"",M78/N78) -> 0.2826087 | P78: 0 | Q78: =IF(P78="","",IF(P78=0,"Free","Paid")) -> Free | S78: 3 | T78: 6 | U78: 3.6 | V78: =IF(OR(U78="",M78="",M78=0),"",U78/(M78*7)) -> 0.1978022 | W78: Yes | Y78: Running SQL queries and Python scripts to extract and clean datasets, Creating interactive dashboards and visualizations in Tableau, Performing statistical analysis and generating insights reports
A79: U0192 | C79: =IF(B79="","",IF(B79<18,"Under 18",IF(B79<25,"18-24",IF(B79<35,"25-34",IF(B79<45,"35-44","45+"))))) | D79: Male | E79: Kenya | F79: Professional | G79: High School | H79: Administrative Assistant | I79: Business & Admin | J79: 557 | K79: ChatGPT | L79: Office Work | M79: 9.9 | N79: 8.5 | O79: =IF(OR(M79="",N79=""),"",M79/N79) -> 1.1647059 | P79: 0 | Q79: =IF(P79="","",IF(P79=0,"Free","Paid")) -> Free | R79: 8.8 | S79: 5 | T79: 9 | U79: 16.2 | V79: =IF(OR(U79="",M79="",M79=0),"",U79/(M79*7)) -> 0.23376623 | W79: Yes | X79: AI hrs exceed work/study hrs (kept)
A80: U0113 | B80: 25 | C80: =IF(B80="","",IF(B80<18,"Under 18",IF(B80<25,"18-24",IF(B80<35,"25-34",IF(B80<45,"35-44","45+"))))) -> 25-34 | D80: Female | E80: Germany | F80: Professional | G80: Master's | H80: Senior Software Developer / Softwareentwicklerin | I80: Software & IT | J80: 6851 | K80: Google Gemini | L80: Coding | M80: 4.1 | O80: =IF(OR(M80="",N80=""),"",M80/N80) | P80: 0 | Q80: =IF(P80="","",IF(P80=0,"Free","Paid")) -> Free | R80: 6 | S80: 4 | T80: 7 | U80: 7.2 | V80: =IF(OR(U80="",M80="",M80=0),"",U80/(M80*7)) -> 0.25087108 | W80: Yes | Y80: Code generation and optimization using AI assistants, automated testing and bug detection with AI tools, documentation generation from code comments, refactoring legacy code with AI suggestions
A81: U0254 | B81: 46 | C81: =IF(B81="","",IF(B81<18,"Under 18",IF(B81<25,"18-24",IF(B81<35,"25-34",IF(B81<45,"35-44","45+"))))) -> 45+ | D81: Female | E81: United Kingdom | F81: Professional | G81: Bachelor's | H81: Customer Support Manager | I81: Customer Support | J81: 3159 | K81: Perplexity AI | L81: Customer Support | M81: 1.9 | N81: 8.6 | O81: =IF(OR(M81="",N81=""),"",M81/N81) -> 0.22093023 | P81: 0 | Q81: =IF(P81="","",IF(P81=0,"Free","Paid")) -> Free | R81: 3.4 | T81: 7 | U81: 4.1 | V81: =IF(OR(U81="",M81="",M81=0),"",U81/(M81*7)) -> 0.30827068 | W81: Yes | Y81: Using AI chatbots to handle routine customer inquiries, training support staff on AI tools, monitoring AI-assisted ticket resolution quality
A82: U0171 | B82: 34 | C82: =IF(B82="","",IF(B82<18,"Under 18",IF(B82<25,"18-24",IF(B82<35,"25-34",IF(B82<45,"35-44","45+"))))) -> 25-34 | D82: Female | E82: United States | F82: Professional | G82: High School | H82: Data Entry Specialist | I82: Data & Analytics | J82: 3878 | L82: Data Analysis | M82: 4.8 | N82: 8.7 | O82: =IF(OR(M82="",N82=""),"",M82/N82) -> 0.55172414 | P82: 30 | Q82: =IF(P82="","",IF(P82=0,"Free","Paid")) -> Paid | R82: 7.7 | S82: 3 | T82: 6 | U82: 5.7 | V82: =IF(OR(U82="",M82="",M82=0),"",U82/(M82*7)) -> 0.16964286 | W82: No | Y82: Organizing customer datasets with Excel and Python scripts, creating automated reports using AI-powered analytics tools, cleaning and validating data quality for business intelligence dashboards
A83: U0088 | B83: 24 | C83: =IF(B83="","",IF(B83<18,"Under 18",IF(B83<25,"18-24",IF(B83<35,"25-34",IF(B83<45,"35-44","45+"))))) -> 18-24 | D83: Male | E83: India | F83: Professional | G83: High School | H83: Data Entry Operator | I83: Data & Analytics | J83: 1761 | K83: Google Gemini | L83: Data Analysis | M83: 0.6 | N83: 10.5 | O83: =IF(OR(M83="",N83=""),"",M83/N83) -> 0.057142857 | P83: 50 | Q83: =IF(P83="","",IF(P83=0,"Free","Paid")) -> Paid | R83: 3.3 | S83: 3 | T83: 5 | U83: 4.2 | V83: =IF(OR(U83="",M83="",M83=0),"",U83/(M83*7)) -> 1 | W83: Yes | Y83: Data cleaning and validation using Python scripts, Excel spreadsheet automation with AI tools, generating automated reports from raw datasets
A84: U0127 | B84: 25 | C84: =IF(B84="","",IF(B84<18,"Under 18",IF(B84<25,"18-24",IF(B84<35,"25-34",IF(B84<45,"35-44","45+"))))) -> 25-34 | D84: Male | E84: Canada | F84: Student | G84: PhD | H84: Artificial Intelligence Research Student | I84: Software & IT | J84: 0 | K84: ChatGPT | L84: Studying | M84: 1.9 | N84: 2.1 | O84: =IF(OR(M84="",N84=""),"",M84/N84) -> 0.9047619 | P84: 10 | Q84: =IF(P84="","",IF(P84=0,"Free","Paid")) -> Paid | R84: 5.5 | S84: 3 | T84: 5 | U84: 2.9 | V84: =IF(OR(U84="",M84="",M84=0),"",U84/(M84*7)) -> 0.21804511 | W84: Maybe | Y84: Literature review and paper summarization, debugging and optimizing machine learning code, generating research hypotheses and experiment design, analyzing complex datasets and statistical modeling
A85: U0108 | B85: 29 | C85: =IF(B85="","",IF(B85<18,"Under 18",IF(B85<25,"18-24",IF(B85<35,"25-34",IF(B85<45,"35-44","45+"))))) -> 25-34 | D85: Female | E85: India | F85: Professional | G85: Master's | H85: Digital Content Strategist | I85: Content, Media & Writing | J85: 2090 | K85: ChatGPT | L85: Content Creation | M85: 1.3 | N85: 9.9 | O85: =IF(OR(M85="",N85=""),"",M85/N85) -> 0.13131313 | P85: 0 | Q85: =IF(P85="","",IF(P85=0,"Free","Paid")) -> Free | R85: 4.3 | S85: 3 | T85: 7 | U85: 2.6 | V85: =IF(OR(U85="",M85="",M85=0),"",U85/(M85*7)) -> 0.28571429 | W85: Yes | Y85: AI-assisted blog writing and SEO optimization, social media caption generation, video script creation with AI tools, content calendar planning using AI analytics
A86: U0055 | B86: 30 | C86: =IF(B86="","",IF(B86<18,"Under 18",IF(B86<25,"18-24",IF(B86<35,"25-34",IF(B86<45,"35-44","45+"))))) -> 25-34 | D86: Male | E86: Philippines | F86: Professional | G86: Master's | H86: Senior Software Engineer | I86: Software & IT | J86: 579 | K86: Microsoft Copilot | L86: Coding | M86: 3.8 | N86: 7.4 | O86: =IF(OR(M86="",N86=""),"",M86/N86) -> 0.51351351 | P86: 0 | Q86: =IF(P86="","",IF(P86=0,"Free","Paid")) -> Free | R86: 6.1 | S86: 4 | T86: 6 | U86: 9.4 | V86: =IF(OR(U86="",M86="",M86=0),"",U86/(M86*7)) -> 0.35338346 | W86: Maybe | Y86: Code review and optimization using AI assistants, automated testing and debugging with AI tools, API development and integration, documentation generation
A87: U0251 | B87: 24 | C87: =IF(B87="","",IF(B87<18,"Under 18",IF(B87<25,"18-24",IF(B87<35,"25-34",IF(B87<45,"35-44","45+"))))) -> 18-24 | D87: Male | E87: United Kingdom | F87: Student | G87: Bachelor's | H87: Molecular Biology Student | I87: Science & Research | J87: 0 | K87: Microsoft Copilot | L87: Research | M87: 1.3 | N87: 4.8 | O87: =IF(OR(M87="",N87=""),"",M87/N87) -> 0.27083333 | P87: 0 | Q87: =IF(P87="","",IF(P87=0,"Free","Paid")) -> Free | R87: 5.2 | S87: 4 | T87: 7 | U87: 2.7 | V87: =IF(OR(U87="",M87="",M87=0),"",U87/(M87*7)) -> 0.2967033 | W87: Yes | Y87: Literature review and scientific paper analysis, data analysis and statistical interpretation, hypothesis generation and research methodology planning
A88: U0248 | C88: =IF(B88="","",IF(B88<18,"Under 18",IF(B88<25,"18-24",IF(B88<35,"25-34",IF(B88<45,"35-44","45+"))))) | D88: Female | E88: Australia | F88: Professional | G88: Master's | H88: Senior Content Strategist | I88: Content, Media & Writing | J88: 6779 | K88: ChatGPT | L88: Content Creation | M88: 2.3 | N88: 11.2 | O88: =IF(OR(M88="",N88=""),"",M88/N88) -> 0.20535714 | P88: 0 | Q88: =IF(P88="","",IF(P88=0,"Free","Paid")) -> Free | R88: 4.8 | S88: 3 | U88: 2.4 | V88: =IF(OR(U88="",M88="",M88=0),"",U88/(M88*7)) -> 0.14906832 | W88: No | X88: Age implausible, blanked | Y88: Generating blog content using AI writing assistants, creating social media copy with AI tools, editing and refining multimedia content with AI enhancement software, developing content calendars and briefs
A89: U0107 | B89: 33 | C89: =IF(B89="","",IF(B89<18,"Under 18",IF(B89<25,"18-24",IF(B89<35,"25-34",IF(B89<45,"35-44","45+"))))) -> 25-34 | D89: Male | E89: United Kingdom | F89: Professional | G89: PhD | H89: Senior Machine Learning Engineer | I89: Software & IT | J89: 8205 | K89: ChatGPT | L89: Coding | M89: 1.5 | N89: 8.4 | O89: =IF(OR(M89="",N89=""),"",M89/N89) -> 0.17857143 | P89: 10 | Q89: =IF(P89="","",IF(P89=0,"Free","Paid")) -> Paid | R89: 5 | S89: 4 | T89: 7 | U89: 1.8 | V89: =IF(OR(U89="",M89="",M89=0),"",U89/(M89*7)) -> 0.17142857 | W89: Yes | Y89: Code generation and debugging with AI assistants, algorithm optimization using neural networks, automated testing and code review with AI tools
A90: U0194 | B90: 40 | C90: =IF(B90="","",IF(B90<18,"Under 18",IF(B90<25,"18-24",IF(B90<35,"25-34",IF(B90<45,"35-44","45+"))))) -> 35-44 | D90: Male | E90: India | F90: Professional | G90: Master's | H90: Senior Data Scientist | I90: Data & Analytics | J90: 1575 | K90: ChatGPT | L90: Data Analysis | M90: 0.7 | N90: 8.3 | O90: =IF(OR(M90="",N90=""),"",M90/N90) -> 0.084337349 | P90: 0 | Q90: =IF(P90="","",IF(P90=0,"Free","Paid")) -> Free | R90: 3.8 | S90: 4 | T90: 8 | U90: 0.6 | V90: =IF(OR(U90="",M90="",M90=0),"",U90/(M90*7)) -> 0.12244898 | W90: No | Y90: Building predictive models using machine learning, Processing large datasets with Python/SQL, Creating automated dashboards and reports, Performing statistical analysis on business metrics
A91: U0026 | B91: 54 | C91: =IF(B91="","",IF(B91<18,"Under 18",IF(B91<25,"18-24",IF(B91<35,"25-34",IF(B91<45,"35-44","45+"))))) -> 45+ | D91: Female | E91: India | F91: Professional | G91: Bachelor's | H91: Administrative Assistant | I91: Business & Admin | J91: 2464 | K91: Google Gemini | L91: Office Work | M91: 3.9 | N91: 7.6 | O91: =IF(OR(M91="",N91=""),"",M91/N91) -> 0.51315789 | P91: 0 | Q91: =IF(P91="","",IF(P91=0,"Free","Paid")) -> Free | R91: 7.7 | S91: 4 | T91: 8 | U91: 6.8 | V91: =IF(OR(U91="",M91="",M91=0),"",U91/(M91*7)) -> 0.24908425 | W91: Yes | Y91: Email management and scheduling with AI tools, Document formatting and data entry using automation software, Report generation and analysis with spreadsheet AI features
A92: U0095 | B92: 43 | C92: =IF(B92="","",IF(B92<18,"Under 18",IF(B92<25,"18-24",IF(B92<35,"25-34",IF(B92<45,"35-44","45+"))))) -> 35-44 | D92: Female | E92: Pakistan | F92: Professional | G92: Master's | H92: Content Strategist & Technical Writer | I92: Content, Media & Writing | J92: 730 | K92: ChatGPT | L92: Writing | M92: 1.6 | N92: 9.7 | O92: =IF(OR(M92="",N92=""),"",M92/N92) -> 0.16494845 | P92: 20 | Q92: =IF(P92="","",IF(P92=0,"Free","Paid")) -> Paid | R92: 5.1 | S92: 4 | T92: 5 | U92: 4.7 | V92: =IF(OR(U92="",M92="",M92=0),"",U92/(M92*7)) -> 0.41964286 | W92: Maybe | Y92: AI-assisted article writing and research, document translation and localization, automated report generation, editing and proofreading with AI tools
A93: U0120 | B93: 31 | C93: =IF(B93="","",IF(B93<18,"Under 18",IF(B93<25,"18-24",IF(B93<35,"25-34",IF(B93<45,"35-44","45+"))))) -> 25-34 | D93: Male | E93: India | F93: Student | G93: Undergraduate | H93: Electronics Engineering Student | I93: Engineering | J93: 157 | K93: ChatGPT | L93: Studying | M93: 0.9 | N93: 6.4 | O93: =IF(OR(M93="",N93=""),"",M93/N93) -> 0.140625 | P93: 25 | Q93: =IF(P93="","",IF(P93=0,"Free","Paid")) -> Paid | R93: 3.7 | S93: 4 | T93: 6 | U93: 0 | V93: =IF(OR(U93="",M93="",M93=0),"",U93/(M93*7)) -> 0 | Y93: Using AI to solve complex circuit problems, generating practice exam questions with solutions, summarizing technical textbooks and research papers
A94: U0049 | B94: 25 | C94: =IF(B94="","",IF(B94<18,"Under 18",IF(B94<25,"18-24",IF(B94<35,"25-34",IF(B94<45,"35-44","45+"))))) -> 25-34 | D94: Female | E94: United Kingdom | F94: Professional | H94: Junior Software Developer | I94: Software & IT | J94: 2945 | K94: Perplexity AI | L94: Coding | N94: 11.3 | O94: =IF(OR(M94="",N94=""),"",M94/N94) | P94: 20 | Q94: =IF(P94="","",IF(P94=0,"Free","Paid")) -> Paid | R94: 9.4 | S94: 3 | T94: 8 | U94: 15.1 | V94: =IF(OR(U94="",M94="",M94=0),"",U94/(M94*7)) | W94: Yes | Y94: Writing Python scripts with AI code completion, debugging code errors using ChatGPT, generating SQL queries for database management, refactoring JavaScript functions with AI assistance
A95: U0032 | C95: =IF(B95="","",IF(B95<18,"Under 18",IF(B95<25,"18-24",IF(B95<35,"25-34",IF(B95<45,"35-44","45+"))))) | D95: Male | E95: Germany | F95: Student | G95: High School | H95: German Literature Student | I95: Content, Media & Writing | J95: 366 | K95: ChatGPT | L95: Writing | M95: 0.6 | N95: 7.6 | O95: =IF(OR(M95="",N95=""),"",M95/N95) -> 0.078947368 | P95: 25 | Q95: =IF(P95="","",IF(P95=0,"Free","Paid")) -> Paid | R95: 4.1 | T95: 6 | U95: 3 | V95: =IF(OR(U95="",M95="",M95=0),"",U95/(M95*7)) -> 0.71428571 | W95: Yes | Y95: Essay structure planning, grammar and spelling correction, essay topic research, writing feedback and revision suggestions
A96: U0073 | C96: =IF(B96="","",IF(B96<18,"Under 18",IF(B96<25,"18-24",IF(B96<35,"25-34",IF(B96<45,"35-44","45+"))))) | D96: Male | E96: Canada | F96: Student | G96: Undergraduate | H96: Environmental Science Student | I96: Science & Research | J96: 397 | K96: Google Gemini | L96: Research | M96: 5.4 | N96: 6.5 | O96: =IF(OR(M96="",N96=""),"",M96/N96) -> 0.83076923 | P96: 0 | Q96: =IF(P96="","",IF(P96=0,"Free","Paid")) -> Free | R96: 9.3 | S96: 3 | T96: 8 | U96: 13.1 | V96: =IF(OR(U96="",M96="",M96=0),"",U96/(M96*7)) -> 0.34656085 | W96: Yes | Y96: Literature review and paper summarization, Data analysis for research projects, Hypothesis generation for experiments, Academic writing and citation organization
A97: U0007 | B97: 24 | C97: =IF(B97="","",IF(B97<18,"Under 18",IF(B97<25,"18-24",IF(B97<35,"25-34",IF(B97<45,"35-44","45+"))))) -> 18-24 | D97: Male | E97: Germany | F97: Student | G97: Master's | H97: Machine Learning Research Student | I97: Software & IT | J97: 134 | K97: Claude | L97: Research | M97: 3.6 | N97: 6.5 | O97: =IF(OR(M97="",N97=""),"",M97/N97) -> 0.55384615 | P97: 20 | Q97: =IF(P97="","",IF(P97=0,"Free","Paid")) -> Paid | S97: 2 | T97: 6 | U97: 5.2 | V97: =IF(OR(U97="",M97="",M97=0),"",U97/(M97*7)) -> 0.20634921 | W97: Maybe | Y97: Literature review and paper summarization, Training neural networks for experimental validation, Data analysis and statistical modeling
A98: U0285 | B98: 35 | C98: =IF(B98="","",IF(B98<18,"Under 18",IF(B98<25,"18-24",IF(B98<35,"25-34",IF(B98<45,"35-44","45+"))))) -> 35-44 | D98: Male | E98: Philippines | F98: Professional | G98: Bachelor's | H98: Content Writer | I98: Content, Media & Writing | J98: 1354 | K98: ChatGPT | L98: Writing | M98: 5 | N98: 6.9 | O98: =IF(OR(M98="",N98=""),"",M98/N98) -> 0.72463768 | P98: 20 | Q98: =IF(P98="","",IF(P98=0,"Free","Paid")) -> Paid | R98: 6.2 | S98: 2 | T98: 6 | U98: 12 | V98: =IF(OR(U98="",M98="",M98=0),"",U98/(M98*7)) -> 0.34285714 | W98: Yes
A99: U0221 | B99: 31 | C99: =IF(B99="","",IF(B99<18,"Under 18",IF(B99<25,"18-24",IF(B99<35,"25-34",IF(B99<45,"35-44","45+"))))) -> 25-34 | E99: Brazil | F99: Student | G99: High School | H99: Software Development Student | I99: Software & IT | J99: 191 | K99: Claude | L99: Coding | M99: 1.9 | N99: 5.1 | O99: =IF(OR(M99="",N99=""),"",M99/N99) -> 0.37254902 | P99: 0 | Q99: =IF(P99="","",IF(P99=0,"Free","Paid")) -> Free | R99: 4.8 | S99: 4 | T99: 7 | U99: 4.8 | V99: =IF(OR(U99="",M99="",M99=0),"",U99/(M99*7)) -> 0.36090226 | W99: Yes | Y99: Debugging Python code with AI assistance, generating boilerplate code templates, learning JavaScript syntax through AI explanations
A100: U0279 | B100: 35 | C100: =IF(B100="","",IF(B100<18,"Under 18",IF(B100<25,"18-24",IF(B100<35,"25-34",IF(B100<45,"35-44","45+"))))) -> 35-44 | D100: Male | E100: Australia | F100: Professional | G100: Bachelor's | H100: Senior Software Developer | I100: Software & IT | J100: 6399 | K100: ChatGPT | L100: Coding | M100: 1.3 | N100: 8.1 | O100: =IF(OR(M100="",N100=""),"",M100/N100) -> 0.16049383 | P100: 20 | Q100: =IF(P100="","",IF(P100=0,"Free","Paid")) -> Paid | R100: 3.1 | S100: 3 | T100: 4 | U100: 4.3 | V100: =IF(OR(U100="",M100="",M100=0),"",U100/(M100*7)) -> 0.47252747 | W100: No | Y100: Code review and debugging using AI assistants, automated testing script generation, documentation and comment generation, API integration optimization
...

Sheet Cleaning_Log
A1: Cleaning log
A2: What was wrong with the file, what was done about it, and how much of the data it touched.
A4: Rows in original file | B4: =COUNTA(Raw_Data!A:A)-1 -> 300
A5: Rows after removing duplicates | B5: =COUNTA(Clean_Data!A:A)-1 -> 288
A6: Columns in original file | B6: 19
A7: Columns in clean file (added 6) | B7: 25
A9: Step | B9: What was done | C9: Rows / cells affected
A10: Removed exact duplicate rows | B10: 12 rows were identical copies of another row (same User_ID and all fields) | C10: 12
A11: Converted Age to a number | B11: Stripped units/symbols such as "$", "hrs", "yrs" and thousands commas | C11: 12
A12: Converted Monthly_Income to a number | B12: Stripped units/symbols such as "$", "hrs", "yrs" and thousands commas | C12: 6
A13: Converted AI_Usage_Hours_Per_Day to a number | B13: Stripped units/symbols such as "$", "hrs", "yrs" and thousands commas | C13: 21
A14: Converted Work_or_Study_Hours_Per_Day to a number | B14: Stripped units/symbols such as "$", "hrs", "yrs" and thousands commas | C14: 12
A15: Converted Time_Saved_Hours_Per_Week to a number | B15: Stripped units/symbols such as "$", "hrs", "yrs" and thousands commas | C15: 15
A16: Converted Monthly_AI_Cost to a number | B16: Stripped units/symbols such as "$", "hrs", "yrs" and thousands commas | C16: 15
A17: Standardized Gender | B17: 11 spellings (male, MALE, M, F, FEMALE, Non-binary...) collapsed to Male, Female, Other / Non-binary | C17: 63
A18: Standardized Country | B18: Fixed casing (brazil -> Brazil) and merged U.K. and United States of America into the standard names | C18: 14
A19: Standardized Education_Level | B19: 16 variants reduced to 6 levels: High School, Diploma, Undergraduate, Bachelor's, Master's, PhD (Undergraduate = currently enrolled, kept separate from Bachelor's = completed) | C19: 16
A20: Standardized AI_Tool | B20: Merged ChatGPT / chatgpt / Chat GPT, Copilot / Microsoft Copilot, Gemini / Google Gemini, claude / Claude | C20: 16
A21: Blanked impossible Age | B21: Age above 90 is not credible for a working professional or a student (found 97 for a student) | C21: 2
... A27: Missing values | B27: Left blank, never guessed or averaged in. Every summary formula ignores blanks, so averages use only real answers. See the completeness table | C27: 215
A28: Counts above were measured in Python during cleaning and typed in here. They are a record of what happened, not live formulas.
A31: Completeness by column (clean file)
A32: Column | B32: Blank cells | C32: % filled
A33: User_ID | B33: =SUMPRODUCT(--(LEN(Clean_Data!$A$2:$A$289)=0)) -> 0 | C33: =1-B33/COUNTA(Clean_Data!$A$2:$A$289) -> 1
A34: Age | B34: =SUMPRODUCT(--(LEN(Clean_Data!$B$2:$B$289)=0)) -> 25 | C34: =1-B34/COUNTA(Clean_Data!$A$2:$A$289) -> 0.91319444
A35: Age_Group | B35: =SUMPRODUCT(--(LEN(Clean_Data!$C$2:$C$289)=0)) -> 25 | C35: =1-B35/COUNTA(Clean_Data!$A$2:$A$289) -> 0.91319444
A36: Gender | B36: =SUMPRODUCT(--(LEN(Clean_Data!$D$2:$D$289)=0)) -> 10 | C36: =1-B36/COUNTA(Clean_Data!$A$2:$A$289) -> 0.96527778
A37: Country | B37: =SUMPRODUCT(--(LEN(Clean_Data!$E$2:$E$289)=0)) -> 10 | C37: =1-B37/COUNTA(Clean_Data!$A$2:$A$289) -> 0.96527778
A38: User_Type | B38: =SUMPRODUCT(--(LEN(Clean_Data!$F$2:$F$289)=0)) -> 0 | C38: =1-B38/COUNTA(Clean_Data!$A$2:$A$289) -> 1
A39: Education_Level | B39: =SUMPRODUCT(--(LEN(Clean_Data!$G$2:$G$289)=0)) -> 12 | C39: =1-B39/COUNTA(Clean_Data!$A$2:$A$289) -> 0.95833333
A40: Profession | B40: =SUMPRODUCT(--(LEN(Clean_Data!$H$2:$H$289)=0)) -> 14 | C40: =1-B40/COUNTA(Clean_Data!$A$2:$A$289) -> 0.95138889
A41: Profession_Group | B41: =SUMPRODUCT(--(LEN(Clean_Data!$I$2:$I$289)=0)) -> 14 | C41: =1-B41/COUNTA(Clean_Data!$A$2:$A$289) -> 0.95138889
A42: Monthly_Income | B42: =SUMPRODUCT(--(LEN(Clean_Data!$J$2:$J$289)=0)) -> 11 | C42: =1-B42/COUNTA(Clean_Data!$A$2:$A$289) -> 0.96180556
A43: AI_Tool | B43: =SUMPRODUCT(--(LEN(Clean_Data!$K$2:$K$289)=0)) -> 10 | C43: =1-B43/COUNTA(Clean_Data!$A$2:$A$289) -> 0.96527778
A44: AI_Purpose | B44: =SUMPRODUCT(--(LEN(Clean_Data!$L$2:$L$289)=0)) -> 13 | C44: =1-B44/COUNTA(Clean_Data!$A$2:$A$289) -> 0.95486111
A45: AI_Hours_Per_Day | B45: =SUMPRODUCT(--(LEN(Clean_Data!$M$2:$M$289)=0)) -> 8 | C45: =1-B45/COUNTA(Clean_Data!$A$2:$A$289) -> 0.97222222
A46: Work_Study_Hours_Per_Day | B46: =SUMPRODUCT(--(LEN(Clean_Data!$N$2:$N$289)=0)) -> 9 | C46: =1-B46/COUNTA(Clean_Data!$A$2:$A$289) -> 0.96875
A47: AI_Share_of_Day | B47: =SUMPRODUCT(--(LEN(Clean_Data!$O$2:$O$289)=0)) -> 17 | C47: =1-B47/COUNTA(Clean_Data!$A$2:$A$289) -> 0.94097222
A48: Monthly_AI_Cost | B48: =SUMPRODUCT(--(LEN(Clean_Data!$P$2:$P$289)=0)) -> 12 | C48: =1-B48/COUNTA(Clean_Data!$A$2:$A$289) -> 0.95833333
A49: Plan_Type | B49: =SUMPRODUCT(--(LEN(Clean_Data!$Q$2:$Q$289)=0)) -> 12 | C49: =1-B49/COUNTA(Clean_Data!$A$2:$A$289) -> 0.95833333
A50: Productivity_Score | B50: =SUMPRODUCT(--(LEN(Clean_Data!$R$2:$R$289)=0)) -> 14 | C50: =1-B50/COUNTA(Clean_Data!$A$2:$A$289) -> 0.95138889
A51: Accuracy_Rating | B51: =SUMPRODUCT(--(LEN(Clean_Data!$S$2:$S$289)=0)) -> 14 | C51: =1-B51/COUNTA(Clean_Data!$A$2:$A$289) -> 0.95138889
A52: Satisfaction_Score | B52: =SUMPRODUCT(--(LEN(Clean_Data!$T$2:$T$289)=0)) -> 7 | C52: =1-B52/COUNTA(Clean_Data!$A$2:$A$289) -> 0.97569444
A53: Time_Saved_Hours_Per_Week | B53: =SUMPRODUCT(--(LEN(Clean_Data!$U$2:$U$289)=0)) -> 10 | C53: =1-B53/COUNTA(Clean_Data!$A$2:$A$289) -> 0.96527778
A54: Hours_Saved_per_AI_Hour | B54: =SUMPRODUCT(--(LEN(Clean_Data!$V$2:$V$289)=0)) -> 18 | C54: =1-B54/COUNTA(Clean_Data!$A$2:$A$289) -> 0.9375
A55: Would_Recommend | B55: =SUMPRODUCT(--(LEN(Clean_Data!$W$2:$W$289)=0)) -> 5 | C55: =1-B55/COUNTA(Clean_Data!$A$2:$A$289) -> 0.98263889
A56: Tasks_Performed | B56: =SUMPRODUCT(--(LEN(Clean_Data!$Y$2:$Y$289)=0)) -> 17 | C56: =1-B56/COUNTA(Clean_Data!$A$2:$A$289) -> 0.94097222
A59: Notes and assumptions
A60: Scales are not defined in the source. Productivity and Satisfaction look like 1 to 10, Accuracy looks like 1 to 5. They are treated that way here.
A61: Monthly_Income has no currency in the source. Values are shown as plain numbers and are not converted.
A62: Missing answers were left blank, not filled with averages. A blank never counts as zero.
A63: Data_Flags lists records that look odd but were kept. Only impossible values (age 97, 23 AI hours a day, 250,000 student income) were blanked.
A64: New columns Age_Group, AI_Share_of_Day, Plan_Type and Hours_Saved_per_AI_Hour are formulas, so they update if a source value is edited.
A65: Raw_Data is the untouched original, kept for audit.

Sheet Raw_Data
A1: User_ID | B1: Age | C1: Gender | D1: Country | E1: User_Type | F1: Education_Level | G1: Profession | H1: Monthly_Income | I1: AI_Tool | J1: AI_Purpose | K1: AI_Usage_Hours_Per_Day | L1: Tasks_Performed | M1: Monthly_AI_Cost | N1: Productivity_Score | O1: Accuracy_Rating | P1: Satisfaction_Score | Q1: Time_Saved_Hours_Per_Week | R1: Work_or_Study_Hours_Per_Day | S1: Would_Recommend
A2: U0269 | B2: 30 | C2: Male | D2: United Kingdom | E2: Professional | F2: Master's | G2: Business Analyst | H2: 5421 | I2: ChatGPT | J2: Office Work | K2: 2 hrs | L2: Data analysis using AI-powered analytics tools, automated report generation, process optimization modelling, AI-assisted business intelligence reporting | N2: 5.3 | O2: 4 | P2: 7 | Q2: 3.9 | R2: 7.3 | S2: Yes
A3: U0217 | B3: 30 | C3: Male | D3: United States | E3: Professional | F3: Bachelor's | G3: Customer Support Specialist | H3: 8903 | I3: ChatGPT | J3: Customer Support | K3: 5.7 | L3: Resolving customer inquiries using AI chatbot platforms, drafting personalized email responses with AI writing assistants, analyzing customer sentiment with AI tools, managing support tickets with AI-powered ticketing systems | M3: 0 | N3: 9.9 | O3: 3 | P3: 9 | Q3: 11.4 | R3: 8.4 hrs | S3: Yes
A4: U0152 | B4: 17 | C4: Male | D4: Canada | E4: Student | G4: Computer Science Student | H4: 402 | I4: Chat GPT | J4: Coding | K4: 1 hrs | M4: 20 | N4: 3.2 | O4: 2 | P4: 4 | Q4: 5.2 | R4: 6.7 | S4: No
A5: U0264 | B5: 35 | C5: FEMALE | D5: Brazil | E5: Professional | F5: Bachelor's | G5: Desenvolvedora de Software / Software Developer | H5: 1367 | I5: Meta AI | J5: Coding | K5: 1.7 | L5: Usar GitHub Copilot para autocompletar código, debugar aplicações com assistência de IA, otimizar algoritmos com sugestões de IA, revisar e refatorar código existente | M5: 20 | N5: 5.6 | O5: 4 | P5: 5 | Q5: 6.4 | R5: 9.6 | S5: Maybe
A6: U0263 | B6: 19 | C6: Female | D6: Canada | E6: Student | F6: Undergraduate | G6: Biology Student | H6: 438 | I6: Perplexity AI | K6: 4.1 | L6: Using AI to generate study summaries for exam preparation, getting help with practice problem solutions, organizing research paper notes | M6: 0 | N6: 4.7 | O6: 4 | P6: 7 | Q6: 9.2 | R6: 6.2 | S6: Yes
A7: U0225 | B7: 19 | D7: United States | E7: Student | F7: Undergraduate | G7: Business Analytics Student | H7: 774 | I7: Meta AI | J7: Data Analysis | K7: 1.5 | L7: Statistical analysis on datasets, data visualization with Python libraries, predictive modeling for coursework, business intelligence report generation | M7: 0 | N7: 5 | O7: 3 | P7: 6 | Q7: 2.9 | R7: 7.4 | S7: No
A8: U0246 | B8: 32 | C8: Male | D8: france | E8: Professional | F8: Bachelor's | G8: Développeur Full Stack | H8: 4466 | I8: ChatGPT | J8: Coding | K8: 1.2 | L8: Automated code review with AI-powered linters, Generated boilerplate code and API endpoints using GitHub Copilot, Debugged complex algorithms with AI assistance, Optimized database queries using AI suggestions | M8: 20 | N8: 3 | O8: 2 | P8: 5 | Q8: 6.6 | R8: 6.4 | S8: Yes
A9: U0177 | B9: 32 | C9: Male | D9: Philippines | E9: Professional | F9: High School | G9: Social Media Content Creator | H9: 486 | I9: ChatGPT | J9: Content Creation | K9: 2 | L9: Creating Instagram/TikTok captions with AI writing tools, Generating YouTube thumbnails and video descriptions using AI design assistants, Editing photos and videos with AI-powered software | M9: 0 | N9: 6.5 | O9: 2 | P9: 5 | Q9: 3.2 hrs | R9: 6.4 | S9: Yes
A10: U0207 | B10: 16 | C10: Male | D10: Philippines | E10: Student | F10: Undergraduate | G10: Digital Media Production Student | H10: 132 | I10: Claude | J10: Content Creation | K10: 1.6 hrs | L10: Creating YouTube video scripts, Designing social media graphics with AI image generators, Writing blog content for tech topics | M10: 30 | N10: 4.7 | O10: 4 | P10: 6 | Q10: 3.8 | R10: 3.8 | S10: Yes
A11: U0167 | B11: 40 | C11: male | D11: india | E11: Professional | F11: High School | H11: 1595 | I11: ChatGPT | J11: Writing | K11: 1.7 | L11: Email copywriting, Social media post creation, Blog article drafting, Product description writing | M11: 10 | O11: 2 | P11: 5 | Q11: 7.5 | R11: 9.4 | S11: Maybe
A12: U0135 | B12: 36 | C12: Female | D12: Pakistan | E12: Professional | F12: Master's | G12: Research Analyst | H12: 856 | I12: chatgpt | J12: Research | K12: 2.7 | L12: Literature review and synthesis using AI-powered databases, Data analysis and pattern recognition, Research paper writing and academic content generation | M12: 0 | O12: 4 | P12: 6 | Q12: 5.7 | R12: 8.7 | S12: Yes
A13: U0211 | B13: 22 | C13: Male | D13: Canada | E13: Student | F13: Undergraduate | G13: Mechanical Engineering Student | H13: 547 | I13: Claude | J13: Research | K13: 5 | L13: Literature review and paper summarization, Data analysis for lab experiments, Generating research hypotheses, Technical documentation and report writing | M13: 0 | N13: 6.6 | O13: 3 | P13: 6 | Q13: 9.8 | R13: 5.6 | S13: No
A14: U0114 | B14: 30 | C14: Female | D14: Australia | E14: Professional | F14: Bachelor's | G14: Software Developer | H14: 3307 | I14: ChatGPT | J14: Coding | K14: 0.8 | L14: Using AI code completion tools for writing Python functions, debugging code with AI-assisted analysis, generating unit test cases with AI tools | M14: 10 | N14: 2.3 | O14: 4 | P14: 4 | Q14: 0.5 | R14: 8 | S14: No
A15: U0191 | B15: 21 | C15: Female | D15: canada | E15: Student | F15: Undergraduate | G15: Software Engineering Student | H15: 387 | I15: ChatGPT | J15: Coding | K15: 5.8 | L15: Debugging code with AI assistance, generating code snippets for assignments, learning programming concepts through AI explanations | M15: 30 | N15: 6.9 | O15: 4 | P15: 8 | Q15: 10.2 | R15: 4.8 | S15: Yes
A16: U0035 | B16: 28 | C16: Male | D16: United Kingdom | E16: Professional | F16: Bachelor's | G16: Data Analyst | H16: 3117 | I16: Claude | J16: Data Analysis | K16: 3.9 | L16: Automated data cleaning and processing with Python scripts, building predictive models using machine learning algorithms, generating interactive dashboards and visualizations in Power BI | M16: 10 | N16: 8.6 | O16: 3 | P16: 8 | Q16: 11.8 | R16: 7.6 hrs | S16: Yes
A17: U0138 | B17: 16 yrs | C17: Female | D17: Canada | E17: Student | F17: Master's | H17: 324 | I17: Microsoft Copilot | J17: Coding | K17: 7.1 | M17: 20 | O17: 2 | P17: 5 | Q17: 11.6 | R17: 3 | S17: No
A18: U0059 | B18: 22 | C18: Male | D18: Canada | E18: Professional | F18: High School | G18: Customer Service Representative | H18: 3546 | I18: Perplexity AI | J18: Customer Support | K18: 1.7 | L18: Responding to customer inquiries via AI chatbots, drafting personalized support emails using AI writing assistants, resolving common technical issues with AI-guided troubleshooting scripts | M18: 0 | N18: 7 | O18: 4 | P18: 7 | Q18: 3.4 | R18: 6.7 | S18: Yes
A19: U0215 | B19: 23 | C19: Male | D19: India | E19: Student | F19: Master's | G19: English Literature Student | H19: 109 | I19: Google Gemini | J19: Writing | K19: 1.5 | L19: Drafting research papers on literary analysis, brainstorming essay outlines, proofreading and refining academic writing, generating content summaries for thesis work | M19: 20 | N19: 3.9 | O19: 3 | P19: 6 | Q19: 3.7 | R19: 3.9 | S19: Yes
A20: U0228 | B20: 22 | C20: male | D20: Kenya | E20: Student | F20: High School | G20: Biology Student | H20: 109 | I20: ChatGPT | J20: Research | K20: 9.6 | L20: Literature review for lab reports, summarizing research papers on molecular genetics, generating study notes from scientific articles | M20: 20 | N20: 7.3 | O20: 4 | P20: 9 | Q20: 19.4 | R20: 5.2 | S20: Yes
A21: U0046 | B21: 61 | C21: Female | D21: Nigeria | E21: Professional | F21: Diploma | G21: Research Technician | H21: 585 | I21: Google Gemini | J21: Research | K21: 23 | L21: Literature review synthesis using AI search tools, Data analysis and statistical reporting with AI-assisted tools, Survey data organization and preliminary findings documentation | M21: 10 | N21: 4.1 | O21: 3 | P21: 4 | Q21: 5.4 | R21: 9.5 | S21: No
A22: U0176 | B22: 24 | C22: Male | D22: India | E22: Professional | F22: Diploma | G22: AI-Powered Customer Support Executive | H22: 1977 | I22: ChatGPT | J22: Customer Support | K22: 0.9 | L22: AI chatbot management and customer query routing, multilingual customer response handling using AI tools, customer complaint analysis and resolution tracking | M22: 10 | N22: 4.1 | O22: 3 | P22: 6 | Q22: 0 | R22: 7.3 | S22: Maybe
A23: U0227 | B23: 23 | C23: M | D23: Pakistan | E23: Student | F23: Master's | G23: English Literature Student | H23: 0 | I23: ChatGPT | J23: Writing | K23: 1.7 hrs | L23: Essay structuring and outline generation, thesis statement refinement, academic paper proofreading and grammar checking, creative writing brainstorming | M23: 20 | N23: 2.8 | O23: 2 | P23: 3 | Q23: 2.7 | R23: 5.4 | S23: No
A24: U0198 | B24: 29 | C24: Female | D24: Germany | E24: Professional | F24: Bachelor's | G24: Kundenservice-Spezialistin / Customer Service Specialist | I24: ChatGPT | J24: Customer Support | K24: 1 | N24: 4 | O24: 3 | P24: 6 | Q24: 2.7 | R24: 8 | S24: Maybe
A25: U0141 | B25: 29 | D25: United Kingdom | E25: Student | F25: High School | G25: Computer Science Student | H25: 0 | I25: Grammarly | J25: Coding | K25: 2.6 | L25: Debugging Python code with AI assistants, generating boilerplate code for web projects, learning algorithms through AI-generated explanations | M25: 10 | N25: 3.7 | O25: 4 | P25: 7 | Q25: 4.8 | R25: 6.2 | S25: Yes
A26: U0205 | B26: 24 | C26: Male | D26: United Kingdom | E26: Student | G26: Mechanical Engineering Student | H26: 444 | I26: Google Gemini | J26: Studying | K26: 1.2 | L26: Analyzing complex physics problems, generating study notes from lecture content, debugging code for coursework projects, creating visual explanations of thermodynamic concepts | M26: 0 | N26: 3.8 | O26: 3 | P26: 5 | Q26: 3 | R26: 7.2 | S26: No
A27: U0209 | B27: 28 | C27: Female | D27: Philippines | E27: Professional | F27: Bachelor's | G27: Digital Content Creator | H27: 392 | I27: ChatGPT | J27: Content Creation | K27: 1.6 | L27: Generating social media captions with AI, Creating blog post drafts using language models, Editing photos and videos with AI tools, Scheduling posts across multiple platforms | M27: 10 | N27: 4 | O27: 2 | P27: 3 | Q27: 4.5 | R27: 7.8 | S27: Yes
A28: U0149 | B28: 23 | C28: M | D28: Brazil | E28: Student | F28: Undergraduate | G28: Computer Science Student | H28: 215 | I28: ChatGPT | J28: Coding | K28: 0.6 | L28: Writing and debugging Python code, generating documentation for projects, optimizing algorithms | M28: 10 | N28: 3 | O28: 4 | P28: 5 | Q28: 0 | R28: 6.5 | S28: No
A29: U0179 | B29: 28 | C29: Male | D29: Brazil | E29: Professional | F29: Bachelor's | G29: Pesquisador de Mercado | H29: 1567 | I29: Microsoft Copilot | J29: Research | K29: 0.7 | L29: Análise de tendências usando ferramentas de IA, extração de dados de fontes públicas, geração de relatórios automatizados, síntese de artigos acadêmicos | M29: $0 | N29: 4 | O29: 3 | P29: 6 | Q29: 4.4 | R29: 8.1 | S29: No
A30: U0016 | B30: 23 yrs | C30: FEMALE | D30: Canada | E30: Student | F30: Undergraduate | G30: Biology Student | I30: ChatGPT | J30: Studying | K30: 7.4 | L30: Using AI to generate practice exam questions, summarizing research papers, explaining complex concepts like cellular respiration | M30: 0 | N30: 8.7 | O30: 3 | P30: 9 | Q30: 12.3 | R30: 6.8 | S30: Yes
A31: U0132 | C31: Male | D31: Australia | E31: Student | G31: Business Administration Student | H31: 0 | I31: ChatGPT | J31: Research | K31: 5.4 | L31: Literature review and source compilation, Data analysis and statistical interpretation, Essay research and citation management | M31: 0 | N31: 7.2 | O31: 4 | P31: 8 | Q31: 10.7 | R31: 4.8 | S31: No
A32: U0008 | B32: 23 | C32: Male | D32: Australia | E32: Student | F32: Undergraduate | G32: English Literature Student | H32: 531 | I32: ChatGPT | J32: Writing | K32: 5.2 | L32: Essay composition and structure planning, grammar checking and proofreading, research paper summarization, creative writing feedback and editing | M32: 0 | N32: 6.7 | P32: 7 | Q32: 12.1 | R32: 7 | S32: Yes
A33: U0162 | B33: 44 | C33: Female | D33: Kenya | E33: Professional | F33: Bachelor's | G33: Research Analyst | H33: 258 | I33: DeepSeek | K33: 3.7 | L33: Literature review automation using AI databases, conducting qualitative data analysis with AI tools, generating research reports and summaries, market research data collection and synthesis | M33: $0 | N33: 4.6 | O33: 5 | P33: 6 | Q33: 5.7 | R33: 6.9 | S33: Yes
A34: U0081 | B34: 23 | C34: Male | D34: Nigeria | E34: Professional | F34: Diploma | G34: Research Assistant | H34: 334 | I34: ChatGPT | J34: Research | K34: 2.3 | L34: Literature review using AI search tools, data analysis with AI-powered statistical software, market research report generation, academic paper summarization | M34: 20 | N34: 3.9 | O34: 2 | P34: 5 | Q34: 2.5 | R34: 7.7 | S34: No
A35: U0014 | B35: 23 | C35: Male | D35: India | E35: Student | F35: high school | G35: Engineering Student | H35: 169 | J35: Studying | K35: 5.4 | L35: Solving physics problems with AI explanation, generating practice questions for exams, translating complex concepts into simplified notes | M35: 0 | N35: 8.1 | O35: 4 | P35: 9 | Q35: 6.8 | R35: 6.9 | S35: Yes
A36: U0278 | B36: 22 | C36: Male | D36: Canada | E36: Student | F36: Undergraduate | G36: Mechanical Engineering Student | H36: 507 | I36: Perplexity AI | J36: Studying | K36: 1.9 | L36: Generating practice problems and solutions for thermodynamics assignments, debugging Python code for finite element analysis projects, summarizing lecture notes on fluid mechanics concepts | M36: 0 | N36: 4.6 | O36: 3 | P36: 4 | Q36: 2 | R36: 4.1 | S36: Yes
A37: U0102 | B37: 18 | C37: Male | D37: Philippines | E37: Student | F37: Undergraduate | G37: Information Technology Student | H37: 0 | I37: Google Gemini | J37: Studying | K37: 1.6 | M37: 0 | N37: 3.3 | O37: 4 | P37: 5 | Q37: 4.3 | R37: 3.2 | S37: Yes
A38: U0258 | B38: 16 | C38: F | E38: Student | F38: Undergraduate | H38: 63 | I38: Perplexity AI | J38: Research | K38: 1.9 | L38: Literature review and paper summarization, Data analysis and interpretation, Research proposal drafting, Scientific article finding and organization | M38: 0 | N38: 3.5 | O38: 3 | P38: 5 | Q38: 3 | R38: 5.4 | S38: Maybe
A39: U0239 | B39: 45 | C39: Male | D39: Pakistan | E39: Professional | F39: Master's | G39: Senior Software Engineer | H39: 887 | J39: Coding | K39: 1.5 | L39: Code review and optimization using AI assistants, automated bug detection and debugging with AI tools, AI-assisted documentation generation, infrastructure code maintenance | M39: $0 | N39: 5.3 | O39: 3 | P39: 5 | Q39: 5.3 | R39: 6.4 | S39: Maybe
A40: U0071 | B40: 30 | D40: India | E40: Professional | F40: Master's | G40: Data Analytics Manager | H40: 1699 | I40: Perplexity AI | J40: Data Analysis | K40: 5.5 | L40: Building predictive models with Python and scikit-learn, Creating business intelligence dashboards in Tableau, Performing statistical analysis on customer datasets | M40: 10 | O40: 4 | P40: 8 | Q40: 6.5 | R40: 7.5 | S40: Yes
A41: U0259 | B41: 43 | C41: Male | D41: Brazil | E41: Professional | F41: PhD | G41: Engenheiro de Software Sênior / Tech Lead | I41: ChatGPT | J41: Coding | K41: 0.6 | L41: Desenvolvimento de algoritmos com assistência de IA, code review automatizado com ferramentas de IA, arquitetura de sistemas de software, mentoria de equipes em práticas de desenvolvimento com IA | M41: 20 | N41: 4 | O41: 2 | P41: 5 | Q41: 0 | R41: 10.1 | S41: Maybe
A42: U0075 | B42: 29 | C42: Male | D42: United States | E42: Professional | F42: Bachelor's | G42: Content Writer | H42: 5260 | I42: Chat GPT | J42: Writing | K42: 1.6 | L42: Drafting blog posts and articles with AI writing assistants, using AI tools to brainstorm content ideas and outline structures, editing and refining generated content for tone and accuracy | M42: 0 | N42: 3.9 | O42: 4 | P42: 5 | Q42: 5.2 | R42: 6.7
A43: U0288 | B43: 36 | C43: M | D43: Pakistan | E43: Professional | F43: Master's | G43: Senior Software Engineer / Technical Lead | H43: 513 | I43: ChatGPT | J43: Coding | K43: 3.7 | L43: Code generation and debugging using AI, automated code review and optimization, rapid prototyping using AI-assisted development frameworks, API design and documentation using AI tools | M43: 0 | N43: 5.7 | O43: 2 | P43: 5 | Q43: 5.8 | R43: 10.1 | S43: Maybe
A44: U0271 | B44: 24 | C44: Female | D44: India | E44: Professional | F44: BA/BSc | G44: Software Developer | H44: 2307 | I44: Grammarly | J44: Coding | K44: 0.6 | L44: Code debugging and optimization using AI assistants, automated test case generation, API integration and documentation, algorithm optimization suggestions | M44: 0 | N44: 4.4 | O44: 4 | P44: 7 | Q44: 1.6 | R44: 12 | S44: Yes
A45: U0070 | B45: 17 | D45: Brazil | E45: Student | F45: Undergraduate | H45: 234 | I45: ChatGPT | J45: Studying | K45: 5.1 | L45: Using AI to solve physics problems, generating study summaries for calculus, translating technical documents from English to Portuguese | M45: 0 | N45: 8.3 | O45: 5 | P45: 9 | Q45: 11.4 | R45: 7.2 | S45: Yes
A46: U0054 | B46: 20 | C46: male | D46: India | E46: Student | F46: High School | G46: Computer Science Student | H46: 206 | I46: Google Gemini | J46: Coding | K46: 2.4 | L46: Debugging code with AI assistants, Learning Python and JavaScript syntax, Solving LeetCode problems with AI explanations | M46: 20 | N46: 5.5 | O46: 3 | P46: 5 | Q46: 7.3 | R46: 8.6 | S46: Yes
A47: U0164 | B47: 44 | C47: Female | D47: Nigeria | E47: Professional | F47: Master's | G47: Research Scientist/Senior Research Officer | H47: 384 | I47: Microsoft Copilot | J47: Research | K47: 0.9 | L47: Literature review automation with AI tools, data analysis and pattern recognition, research paper synthesis and summarization, hypothesis validation using machine learning models | M47: 10 | N47: 3.1 | O47: 3 | P47: 4 | Q47: 1.2 | R47: 7.9 | S47: No
A48: U0219 | B48: 21 | C48: Male | D48: United Kingdom | E48: Student | F48: Master's | G48: Artificial Intelligence and Machine Learning Student | H48: 206 | I48: Gemini | J48: Coding | K48: 9.1 | L48: Debugging Python code with AI-powered IDE plugins, Generating optimization algorithms for data structures, Writing and testing unit tests for complex modules | M48: 30 | N48: 6.5 | O48: 3 | P48: 8 | Q48: 14.9 | R48: 5.4 | S48: Yes
A49: U0036 | B49: 34 | C49: Female | D49: United States | E49: Professional | F49: Master's | G49: Content Strategy Manager | H49: 5669 | I49: ChatGPT | J49: Writing | K49: 8 | L49: Uses AI tools to generate initial content drafts, optimize SEO metadata and headlines, streamline editing and proofreading processes, manage multi-channel content calendars | M49: 0 | N49: 7.3 | O49: 2 | P49: 7 | Q49: 16.3 | R49: 7.4 | S49: Yes
A50: U0057 | B50: 18 | C50: Male | D50: Philippines | E50: Student | F50: High School | G50: English Literature Student | H50: 198 | I50: Perplexity AI | J50: Writing | L50: Essay composition and structure planning, grammar and spelling correction, brainstorming ideas for creative writing assignments | M50: 0 | N50: 6.9 | O50: 2 | P50: 6 | Q50: 7.2 | R50: 7.2 | S50: Maybe
A51: U0060 | C51: Female | D51: Philippines | E51: Student | F51: Bachelor's | H51: 190 | I51: ChatGPT | J51: Research | K51: 7.7 | L51: Literature review and paper summarization, Data analysis for research datasets, Academic paper organization and citation management | N51: 8.4 | O51: 5 | P51: 10 | Q51: 13.6 | R51: 6.8 | S51: Yes
A52: U0226 | B52: 32 | C52: male | D52: Nigeria | E52: Professional | F52: High School | G52: Social Media Content Creator / Digital Marketer | H52: 376 | I52: Claude | J52: Content Creation | K52: 1.3 | L52: Creating engaging social media posts with AI writing tools, Generating captions and hashtags using AI, Editing and optimizing images with AI-powered design tools, Producing video content summaries and descriptions | M52: 20 | N52: 3.3 | O52: 4 | P52: 5 | Q52: 3.2 | R52: 11.6 | S52: Maybe
A53: U0118 | B53: 44 | C53: other | D53: France | E53: Professional | F53: Bachelor's | G53: Responsable de Contenu Digital | H53: 3477 | I53: ChatGPT | J53: Content Creation | K53: 2.2 hrs | L53: Création d'articles de blog avec assistance IA, Génération de contenu pour réseaux sociaux, Optimisation SEO avec outils IA, Édition et révision de textes | M53: 0 | N53: 5 | O53: 4 | Q53: 2.8 | R53: 10.7 | S53: Yes
A54: U0028 | C54: Other | D54: Pakistan | E54: Student | F54: Undergraduate | G54: English Literature Student | H54: 100 | I54: ChatGPT | J54: Writing | K54: 1.2 | L54: Essay drafting and outline generation, academic paper research summarization, creative writing feedback and editing | M54: 50 | N54: 5.8 | O54: 4 | P54: 7 | R54: 5.7 | S54: Yes
A55: U0125 | B55: 26 | D55: Nigeria | E55: Student | F55: High School | G55: Computer Science Student | H55: 0 | I55: ChatGPT | J55: Coding | K55: 0.6 | L55: Debugging Python code with AI code analysis, Writing SQL queries for database projects, Generating HTML/CSS templates for web assignments | M55: 0 | N55: 3.2 | O55: 2 | P55: 5 | Q55: 2.2 hrs | R55: 8.8 | S55: Yes
A56: U0223 | B56: 33 | C56: F | D56: Australia | E56: Professional | F56: Diploma | G56: Marketing Communications Officer | H56: 6197 | I56: ChatGPT | J56: Writing | K56: 1.9 | L56: AI-assisted content writing for social media and marketing campaigns, proofreading and editing copy with AI grammar tools, generating email newsletters and promotional materials | N56: 5.4 | O56: 4 | P56: 7 | Q56: 6 | R56: 11 | S56: Yes
A57: U0243 | B57: 31 | C57: Male | D57: Australia | E57: Professional | F57: Bachelor's | G57: Customer Support Specialist | H57: 5355 | I57: Google Gemini | J57: Customer Support | K57: 4.6 | L57: Drafting customer responses using AI writing assistants, analyzing customer feedback with sentiment analysis tools, resolving FAQs using AI knowledge base systems, escalating complex issues to senior staff | M57: 0 | N57: 8.8 | O57: 2 | P57: 6 | Q57: 11.5 | R57: 8.7 | S57: Yes
A58: U0165 | B58: 22 | C58: Male | D58: brazil | E58: Student | F58: High School | G58: Mechanical Engineering Student | H58: 86 | I58: Google Gemini | J58: Studying | K58: 1.4 | L58: Using AI to solve physics and calculus problems, generating practice exam questions, translating technical documentation from English to Portuguese | M58: $0 | N58: 1.9 | O58: 3 | P58: 5 | Q58: 1.7 | S58: Yes
A59: U0238 | B59: 21 | C59: Male | D59: Pakistan | E59: Student | F59: High School | G59: Digital Media Student | H59: 62 | I59: ChatGPT | J59: Content Creation | K59: 7.2 | L59: Creating social media graphics with AI design tools, Writing blog posts and articles with AI writing assistants, Generating video scripts and editing content with AI video tools | M59: 10 | N59: 6.8 | O59: 4 | P59: 7 | Q59: 13.2 | R59: 6.1 | S59: Yes
A60: U0069 | B60: 32 | C60: Male | D60: Canada | E60: Professional | F60: Bachelor's | G60: Content Marketing Manager | H60: 3337 | I60: ChatGPT | K60: 1.3 | L60: Creating blog posts and web copy with AI writing assistants, editing and refining client proposals, generating social media content calendars and posts | M60: 0 | N60: 3.8 | O60: 4 | P60: 7 | Q60: 2.9 | R60: 7.6 | S60: Yes
A61: U0092 | B61: 22 | C61: Male | D61: Pakistan | E61: Student | F61: Bachelor's | G61: Computer Science Student | H61: 113 | I61: Perplexity AI | J61: Data Analysis | K61: 1 | L61: Statistical analysis of datasets, data visualization using Python libraries, predictive modeling with machine learning algorithms, database query optimization | M61: 0 | N61: 3.2 | O61: 3 | P61: 3 | Q61: 4.2 | R61: 6.5 | S61: No
A62: U0043 | B62: 21 yrs | C62: M | D62: United Kingdom | E62: Student | F62: Undergraduate | G62: Computer Science Student | H62: 118 | I62: Google Gemini | J62: Coding | M62: 0 | N62: 7.6 | O62: 2 | P62: 6 | Q62: 12.4 | R62: 6.3 | S62: Yes
A63: U0084 | B63: 47 yrs | C63: Male | D63: Nigeria | E63: Professional | F63: Bachelor's | G63: Business Intelligence Analyst | H63: 1104 | I63: Grammarly | J63: Data Analysis | K63: 3.4 | L63: Cleaning and processing customer transaction data, generating sales trend reports using Python, creating data visualizations in Power BI dashboards | M63: 20 | N63: 4.9 | O63: 3 | P63: 5 | Q63: 7.4 | R63: 7.3 | S63: No
A64: U0061 | B64: 33 | C64: Male | D64: brazil | E64: Professional | F64: Bachelor's | G64: Desenvolvedor de Software Sênior | H64: 552 | I64: Google Gemini | J64: Coding | K64: 0.5 | L64: Usar GitHub Copilot para completar código, gerar testes unitários com IA, otimizar algoritmos com sugestões de IA, revisar e debugar código com assistentes de IA | M64: 20 | N64: 2.9 | O64: 3 | P64: 5 | Q64: 0.1 | R64: 10.2 | S64: No
A65: U0116 | B65: 20 | C65: Male | D65: India | E65: Student | F65: Undergraduate | G65: Digital Media and Communications Student | H65: 79 | I65: Google Gemini | J65: Content Creation | K65: 3.5 | L65: AI-assisted blog writing and SEO optimization, video scriptwriting and thumbnail design generation, social media content creation and caption generation | M65: 20 | N65: 4.7 | O65: 4 | P65: 7 | Q65: 8.3 | R65: 6.2 | S65: Yes
A66: U0039 | B66: 23 | C66: Male | D66: United Kingdom | E66: Student | F66: Master's | G66: Bioinformatics Student | H66: 614 | I66: Claude | J66: Research | K66: 1 | L66: Literature review automation with AI summarization, designing research methodology frameworks, analyzing genomic datasets using machine learning models, peer review preparation assistance | M66: 20 | N66: 2.5 | O66: 4 | P66: 6 | Q66: 0.7 | R66: 6.6 | S66: Maybe
A67: U0022 | B67: 37 | C67: F | D67: India | E67: Professional | F67: Diploma | G67: Software Developer | H67: 1404 | I67: ChatGPT | J67: Coding | K67: 1.7 | L67: Writing and debugging Python code using AI assistants, automating repetitive coding tasks with AI tools, code review and optimization with AI-powered suggestions | N67: 5.7 | O67: 5 | P67: 7 | Q67: 3.4 | R67: 6.4 | S67: Yes
A68: U0137 | B68: 23 | C68: Other | E68: Student | F68: Master's | G68: Software Engineering Student | H68: 0 | I68: Microsoft Copilot | J68: Coding | K68: 1 | L68: Code debugging and optimization, API development and integration, machine learning model training and implementation | M68: 20 | N68: 3.3 | O68: 3 | P68: 5 | Q68: 2.6 | R68: 6.2 | S68: Yes
A69: U0116 | B69: 20 | C69: Male | D69: India | E69: Student | F69: Undergraduate | G69: Digital Media and Communications Student | H69: 79 | I69: Google Gemini | J69: Content Creation | K69: 3.5 | L69: AI-assisted blog writing and SEO optimization, video scriptwriting and thumbnail design generation, social media content creation and caption generation | M69: 20 | N69: 4.7 | O69: 4 | P69: 7 | Q69: 8.3 | R69: 6.2 | S69: Yes
A70: U0027 | B70: 20 | C70: male | D70: United Kingdom | E70: Student | F70: Undergraduate | G70: Computer Science Student | H70: 0 | I70: ChatGPT | J70: Coding | K70: 1.3 | L70: Debugging code with AI assistance, generating boilerplate code for projects, learning new programming concepts through AI explanations | M70: 0 | N70: 4.8 | O70: 4 | P70: 7 | Q70: 2.9 | R70: 8.1 | S70: Yes
A71: U0268 | B71: 31 | C71: Female | D71: France | E71: Student | F71: Undergraduate | G71: Biology Student | H71: 302 | I71: Google Gemini | J71: Studying | K71: 0.7 hrs | L71: Using AI to generate study summaries, practice exam questions, and lab report writing assistance | M71: 0 | N71: 3.4 | P71: 5 | Q71: 0.8 | R71: 4.5 hrs | S71: Maybe
A72: U0131 | B72: 35 | D72: United States | E72: Professional | F72: Diploma | G72: Administrative Assistant | H72: 5966 | I72: ChatGPT | J72: Office Work | K72: 4.9 | L72: Data entry and document formatting with AI tools, scheduling meetings and managing calendar using AI assistants, generating business reports with AI summarization software, proofreading emails and correspondence using grammar AI | M72: 20 | N72: 5.7 | O72: 3 | P72: 5 | Q72: 11.5 | R72: 9.3 | S72: Yes
A73: U0255 | B73: 28 | C73: Male | D73: Australia | E73: Professional | F73: MA/MSc | G73: Senior Software Engineer | H73: 3610 | I73: Google Gemini | J73: Coding | K73: 4.3 | L73: Code generation and debugging with AI assistants, automated testing and deployment pipeline optimization, machine learning model implementation and optimization | M73: 0 | N73: 6.1 | O73: 3 | P73: 7 | Q73: 6.7 | R73: 8.1 | S73: Yes
A74: U0231 | B74: 22 | C74: male | D74: Nigeria | E74: Professional | F74: Master's | G74: Data Analyst | H74: 1091 | J74: Data Analysis | K74: 2.4 | L74: Building predictive models with machine learning algorithms, Creating automated dashboards for business intelligence, Cleaning and transforming large datasets for analysis | M74: 0 | N74: 5.4 | O74: 4 | P74: 5 | Q74: 2.6 hrs | R74: 8 | S74: Yes
A75: U0067 | B75: 22 | C75: Other | D75: India | E75: Student | F75: Undergraduate | G75: Biotechnology Student | H75: 68 | I75: ChatGPT | K75: 0.7 | L75: Literature review automation, research paper summarization, data analysis and visualization, hypothesis generation | M75: 0 | N75: 4.1 | O75: 4 | P75: 6 | Q75: 2.1 | R75: 8.6 | S75: No
A76: U0234 | C76: Female | D76: Nigeria | E76: Student | F76: Bachelor's | G76: English Literature Student | I76: ChatGPT | J76: Writing | K76: 2.1 | L76: Essay composition and structure planning, grammar and style checking, research paper organization, content brainstorming for creative writing assignments | M76: 0 | N76: 4.7 | O76: 5 | P76: 8 | R76: 5.9 | S76: Yes
A77: U0184 | B77: 36 | C77: Female | D77: Philippines | E77: Professional | F77: Ph.D. | G77: Senior Software Engineer / AI Solutions Architect | H77: 1378 | I77: Perplexity AI | J77: Coding | K77: 2.1 | M77: 0 | N77: 3.8 | O77: 4 | P77: 5 | Q77: 2.8 | R77: 7.8 | S77: Yes
A78: U0096 | B78: 17 | C78: Male | D78: United States | E78: Student | F78: High School | G78: Environmental Science Student | H78: 884 | J78: Research | K78: 7 | M78: 20 | N78: 9.7 | O78: 4 | P78: 10 | Q78: 12.8 | R78: 5.8 | S78: Yes
A79: U0274 | B79: 39 | C79: Female | D79: United States | E79: Professional | F79: Bachelor's | G79: Data Analyst | H79: 3204 | I79: ChatGPT | J79: Data Analysis | K79: 2.6 | L79: Running SQL queries and Python scripts to extract and clean datasets, Creating interactive dashboards and visualizations in Tableau, Performing statistical analysis and generating insights reports | M79: 0 | O79: 3 | P79: 6 | Q79: 3.6 | R79: 9.2 | S79: Yes
A80: U0192 | C80: Male | D80: Kenya | E80: Professional | F80: High School | G80: Administrative Assistant | H80: 557 | I80: ChatGPT | J80: Office Work | K80: 9.9 hrs | M80: 0 | N80: 8.8 | O80: 5 | P80: 9 | Q80: 16.2 | R80: 8.5 | S80: Yes
A81: U0113 | B81: 25 | C81: female | D81: Germany | E81: Professional | F81: Master's | G81: Senior Software Developer / Softwareentwicklerin | H81: 6851 | I81: Google Gemini | J81: Coding | K81: 4.1 | L81: Code generation and optimization using AI assistants, automated testing and bug detection with AI tools, documentation generation from code comments, refactoring legacy code with AI suggestions | M81: 0 | N81: 6 | O81: 4 | P81: 7 | Q81: 7.2 | S81: Yes
A82: U0254 | B82: 46 | C82: Female | D82: United Kingdom | E82: Professional | F82: Bachelor's | G82: Customer Support Manager | H82: 3159 | I82: Perplexity AI | J82: Customer Support | K82: 1.9 | L82: Using AI chatbots to handle routine customer inquiries, training support staff on AI tools, monitoring AI-assisted ticket resolution quality | M82: 0 | N82: 3.4 | P82: 7 | Q82: 4.1 hrs | R82: 8.6 | S82: Yes
A83: U0171 | B83: 34 | C83: Female | D83: United States | E83: Professional | F83: High School | G83: Data Entry Specialist | H83: 3878 | J83: Data Analysis | K83: 4.8 hrs | L83: Organizing customer datasets with Excel and Python scripts, creating automated reports using AI-powered analytics tools, cleaning and validating data quality for business intelligence dashboards | M83: $30 | N83: 7.7 | O83: 3 | P83: 6 | Q83: 5.7 | R83: 8.7 hrs | S83: No
A84: U0088 | B84: 24 | C84: Male | D84: india | E84: Professional | F84: High School | G84: Data Entry Operator | H84: 1761 | I84: Google Gemini | J84: Data Analysis | K84: 0.6 | L84: Data cleaning and validation using Python scripts, Excel spreadsheet automation with AI tools, generating automated reports from raw datasets | M84: 50 | N84: 3.3 | O84: 3 | P84: 5 | Q84: 4.2 | R84: 10.5 | S84: Yes
A85: U0127 | B85: 25 yrs | C85: MALE | D85: Canada | E85: Student | F85: PhD | G85: Artificial Intelligence Research Student | H85: 0 | I85: chatgpt | J85: Studying | K85: 1.9 | L85: Literature review and paper summarization, debugging and optimizing machine learning code, generating research hypotheses and experiment design, analyzing complex datasets and statistical modeling | M85: 10 | N85: 5.5 | O85: 3 | P85: 5 | Q85: 2.9 hrs | R85: 2.1 | S85: Maybe
A86: U0108 | B86: 29 | C86: Female | D86: India | E86: Professional | F86: Master's | G86: Digital Content Strategist | H86: 2090 | I86: Chatgpt | J86: Content Creation | K86: 1.3 | L86: AI-assisted blog writing and SEO optimization, social media caption generation, video script creation with AI tools, content calendar planning using AI analytics | M86: 0 | N86: 4.3 | O86: 3 | P86: 7 | Q86: 2.6 | R86: 9.9 | S86: Yes
A87: U0055 | B87: 30 | C87: Male | D87: Philippines | E87: Professional | F87: Masters | G87: Senior Software Engineer | H87: 579 | I87: Microsoft Copilot | J87: Coding | K87: 3.8 | L87: Code review and optimization using AI assistants, automated testing and debugging with AI tools, API development and integration, documentation generation | M87: 0 | N87: 6.1 | O87: 4 | P87: 6 | Q87: 9.4 hrs | R87: 7.4 | S87: Maybe
A88: U0251 | B88: 24 | C88: M | D88: U.K. | E88: Student | F88: Bachelor's | G88: Molecular Biology Student | H88: 0 | I88: Microsoft Copilot | J88: Research | K88: 1.3 | L88: Literature review and scientific paper analysis, data analysis and statistical interpretation, hypothesis generation and research methodology planning | M88: 0 | N88: 5.2 | O88: 4 | P88: 7 | Q88: 2.7 | R88: 4.8 | S88: Yes
A89: U0059 | B89: 22 | C89: Male | D89: Canada | E89: Professional | F89: High School | G89: Customer Service Representative | H89: 3546 | I89: Perplexity AI | J89: Customer Support | K89: 1.7 | L89: Responding to customer inquiries via AI chatbots, drafting personalized support emails using AI writing assistants, resolving common technical issues with AI-guided troubleshooting scripts | M89: 0 | N89: 7 | O89: 4 | P89: 7 | Q89: 3.4 | R89: 6.7 | S89: Yes
A90: U0248 | B90: 97 | C90: Female | D90: Australia | E90: Professional | F90: Master's | G90: Senior Content Strategist | H90: 6779 | I90: ChatGPT | J90: Content Creation | K90: 2.3 | L90: Generating blog content using AI writing assistants, creating social media copy with AI tools, editing and refining multimedia content with AI enhancement software, developing content calendars and briefs | M90: 0 | N90: 4.8 | O90: 3 | Q90: 2.4 | R90: 11.2 | S90: No
A91: U0107 | B91: 33 | C91: Male | D91: United Kingdom | E91: Professional | F91: PhD | G91: Senior Machine Learning Engineer | H91: 8205 | I91: ChatGPT | J91: Coding | K91: 1.5 | L91: Code generation and debugging with AI assistants, algorithm optimization using neural networks, automated testing and code review with AI tools | M91: 10 | N91: 5 | O91: 4 | P91: 7 | Q91: 1.8 | R91: 8.4 | S91: Yes
A92: U0194 | B92: 40 | C92: Male | D92: India | E92: Professional | F92: Master's | G92: Senior Data Scientist | H92: 1575 | I92: ChatGPT | J92: Data Analysis | K92: 0.7 | L92: Building predictive models using machine learning, Processing large datasets with Python/SQL, Creating automated dashboards and reports, Performing statistical analysis on business metrics | M92: 0 | N92: 3.8 | O92: 4 | P92: 8 | Q92: 0.6 | R92: 8.3 | S92: No
A93: U0026 | B93: 54 | C93: Female | D93: India | E93: Professional | F93: Bachelor's | G93: Administrative Assistant | H93: 2464 | I93: Google Gemini | J93: Office Work | K93: 3.9 | L93: Email management and scheduling with AI tools, Document formatting and data entry using automation software, Report generation and analysis with spreadsheet AI features | M93: 0 | N93: 7.7 | O93: 4 | P93: 8 | Q93: 6.8 hrs | R93: 7.6 | S93: Yes
A94: U0095 | B94: 43 | C94: Female | D94: Pakistan | E94: Professional | F94: Master's | G94: Content Strategist & Technical Writer | H94: 730 | I94: ChatGPT | J94: Writing | K94: 1.6 | L94: AI-assisted article writing and research, document translation and localization, automated report generation, editing and proofreading with AI tools | M94: 20 | N94: 5.1 | O94: 4 | P94: 5 | Q94: 4.7 | R94: 9.7 | S94: Maybe
A95: U0120 | B95: 31 | C95: Male | D95: India | E95: Student | F95: Undergraduate | G95: Electronics Engineering Student | H95: 157 | I95: ChatGPT | J95: Studying | K95: 0.9 | L95: Using AI to solve complex circuit problems, generating practice exam questions with solutions, summarizing technical textbooks and research papers | M95: 25 | N95: 3.7 | O95: 4 | P95: 6 | Q95: 0 | R95: 6.4
A96: U0049 | B96: 25 | C96: Female | D96: United Kingdom | E96: Professional | G96: Junior Software Developer | H96: 2945 | I96: Perplexity AI | J96: Coding | L96: Writing Python scripts with AI code completion, debugging code errors using ChatGPT, generating SQL queries for database management, refactoring JavaScript functions with AI assistance | M96: 20 | N96: 9.4 | O96: 3 | P96: 8 | Q96: 15.1 | R96: 11.3 | S96: Yes
A97: U0032 | C97: Male | D97: Germany | E97: Student | F97: High School | G97: German Literature Student | H97: 366 | I97: ChatGPT | J97: Writing | K97: 0.6 | L97: Essay structure planning, grammar and spelling correction, essay topic research, writing feedback and revision suggestions | M97: $25 | N97: 4.1 | P97: 6 | Q97: 3 | R97: 7.6 | S97: Yes
A98: U0073 | C98: Male | D98: Canada | E98: Student | F98: Undergraduate | G98: Environmental Science Student | H98: 397 | I98: Google Gemini | J98: Research | K98: 5.4 | L98: Literature review and paper summarization, Data analysis for research projects, Hypothesis generation for experiments, Academic writing and citation organization | M98: 0 | N98: 9.3 | O98: 3 | P98: 8 | Q98: 13.1 | R98: 6.5 | S98: Yes
A99: U0007 | B99: 24 | C99: Male | D99: Germany | E99: Student | F99: Master's | G99: Machine Learning Research Student | H99: 134 | I99: Claude | J99: Research | K99: 3.6 | L99: Literature review and paper summarization, Training neural networks for experimental validation, Data analysis and statistical modeling | M99: 20 | O99: 2 | P99: 6 | Q99: 5.2 | R99: 6.5 | S99: Maybe
A100: U0285 | B100: 35 | C100: Male | D100: Philippines | E100: Professional | F100: Bachelor's | G100: Content Writer | H100: 1354 | I100: ChatGPT | J100: Writing | K100: 5 | M100: 20 | N100: 6.2 | O100: 2 | P100: 6 | Q100: 12 | R100: 6.9 | S100: Yes
...
